Workbook

Sheet README
A1: McEasy — FMS comparables benchmark
B3: Built for | C3: Grady Kusmulyadi, McEasy — benchmarking a 2030 target of USD100m ARR.
B4: Built on | C4: 10-Aug-2026. Latest reported full year for each company.
B5: Peer set | C5: Emerging-market SMB fleet operators (Karooooo/Cartrack, Ituran, Powerfleet incl. MiX Telematics history), private VC-backed FMS (Motive, Geotab, Lytx, Gurtam), and the players currently at USD80-250m of revenue (Microlise, CalAmp, Teletrac Navman, Netradyne, ORBCOMM), plus Chinese-listed hardware vendors (Queclink, Streamax) in a separate block and two below-band closest-model comps (Quartix, Fleetio).
B6: Three cuts | C6: The workbook answers the USD100m question three ways, and they disagree with each other in the most useful way possible: what USD100m ARR looked like historically (Cartrack FY2019), who is at that size right now (Microlise, Quartix and peers), and where the big players sit today (Karooooo, Motive, Powerfleet, Ituran).
B8: Sheets
B9: McEasy vs Benchmark | C9: THE ANSWER. McEasy's 2030 model against Cartrack FY2019, with the per-vehicle unit economics that carry the argument, the one claim that needs defending, and bull/base/bear. Start here.
B10: Conservative Cases | C10: 2030 revenue $10m and $20m below plan, re-based month by month from Jul-2026 off actuals. Two drivers each, because a volume miss and a price miss end up in different places. Includes the 2027 cash trough.
B11: Capex Decomposition | C11: The one claim that needs defending, taken apart. Capex per NEW INSTALL (USD54) against a bottom-up bill of materials (USD26-46), why Cartrack's USD177 is not a device cost, and the justifications ranked.
B12: Growth Reality Check | C12: The assumption that IS more aggressive than the benchmark — a 66% ARR CAGR delivered while turning profitable and not raising again.
B13: McEasy Model | C13: Grady's own model, read programmatically from the source file. Yellow cell = the 2030 vehicle count, which drives every per-vehicle figure.
B14: At 100M (Today) | C14: WHO IS AT THIS SIZE RIGHT NOW — revenue USD80-250m. Three labelled blocks: subscription-FMS operators, hardware vendors, and below-band closest models. Start here.
B15: At 100M (Historic) | C15: The same metrics at the year each company crossed ~USD100m ARR. Cartrack FY2019 is the only fully-populated row.
B16: Current Position | C16: The big players at their latest reported year — the destination view. All in USD millions.
B17: Valuation Signals | C17: What the market pays for an FMS business at USD100-250m of revenue, and what it depends on. The dispersion is roughly 20x wide.
B18: Revenue by Country | C18: Geographic mix across every company that discloses one. Karooooo FY2019 and FY2025 disclosed, FY2026 rolled forward; plus Queclink, Streamax, Ituran, Motive and Cartrack subscribers by region.
B19: Revenue by Product | C19: Product-line mix. Recurring versus hardware, Karooooo's Delivery-as-a-Service drag, and Queclink's full device line-up.
B20: Karooooo Path | C20: Cartrack FY2018 to FY2026 in full — the actual trajectory from USD90m to USD325m ARR.
... B23: Sources | C23: Every URL, with what it supports.
B25: The answer, in one paragraph
C26: Cartrack at FY2019 is the benchmark, and the match is far closer than a margin comparison suggests. McEasy's 2030 plan and Cartrack's FY2019 actuals sit 1.1% apart on vehicles (950,000 vs 960,798) and 2.3% apart on EBITDA per vehicle ($56.54 vs $57.85) — at a LOWER price per vehicle ($8.94/month vs $10.72). The 7.7pp EBITDA margin gap is a denominator effect from carrying less low-margin hardware revenue, not a claim to superior operating performance. That collapses the whole investor challenge to one testable number: capex per vehicle of $20.00 against Cartrack's $38.53. Lead with EBITDA per vehicle, never with 52.7%.
B28: Seven things the data says
B29: 1 | C29: USD100m ARR is not one destination — it is at least three different businesses. At that milestone, EBITDA margin across this peer set ranged from roughly 21% (MiX Telematics) to 45% (Cartrack) to deeply negative (Motive), and time from founding ranged from 6 years to 18. Decide which one you are building before you plan the number.
B30: 2 | C30: The company closest to USD100m ARR today is a warning, not a target. Microlise runs ARR of USD78m on USD111m of revenue with a 64% gross margin — and posts a STATUTORY OPERATING LOSS. Its 10% figure is adjusted EBITDA, down from 14%. Cartrack at a comparable ARR in FY2019 ran a 45% EBITDA margin and a 21% net margin. Same scale, same industry, opposite economics.
B31: 3 | C31: The market prices that difference brutally. Microlise carries an enterprise value of 0.39x sales — GBP32m against GBP84m of revenue. Karooooo carries 5.52x. Teletrac Navman, at USD168m of revenue, was sold by a strategic owner for about 1.3x. CalAmp reached USD200m of revenue and 2.7m subscribers, then wiped out its equity in Chapter 11 on a 6.4% EBITDA margin. Reaching USD100m ARR at thin margins creates almost no enterprise value.
B32: 4 | C32: Scale is not what creates margin. Quartix is profitable at HALF the target size — 73% gross, 24% operating, 18% net, 12.5% FCF margin on USD47m of revenue. Pricing power and product mix create margin; revenue does not.
B33: 5 | C33: Cartrack's free-cash-flow margin at USD100m ARR was about 2%, not the 15% it runs today. A 45% EBITDA margin was almost entirely consumed by capex running at 30% of revenue — devices, installation and contract assets. Hardware-subsidised FMS does not self-fund at USD100m.
B34: 6 | C34: Geographic diversification did not drive Cartrack from USD100m to USD325m. South Africa was 73.6% of revenue at the milestone and is still about 74% today; Southeast Asia is 12.6% of the subscriber base after roughly fifteen years. Depth in the home market, not breadth, was the engine. Note the mirror image: Queclink, a device vendor, earns 94% of revenue outside its home market. Exporting hardware and operating a subscription base are different businesses.
B35: 7 | C35: Karooooo management states plainly that Southeast Asian ARPU — Indonesia, Philippines, Thailand — sits materially below South African ARPU and will dilute group ARPU as the mix shifts. For an Indonesia-based company this is the binding constraint, and it makes the subscriber count, not the ARR figure, the real target.
B37: One caution on the framing
C38: Karooooo's current position — USD325m ARR, 18% net margin, 15% FCF margin, dividend-paying — is the destination, not the path, and benchmarking against it will flatter any 2030 model. Those margins reflect twenty-two years of compounding and a dominant position in one market. But the opposite error is just as costly: benchmarking against today's USD100m players alone would suggest the milestone is barely worth reaching. The honest reading needs both. And the real conclusion is that "USD100m ARR by 2030" is an underspecified goal — the same ARR is worth roughly USD40m of enterprise value at Microlise economics and several hundred million at Cartrack economics. Specify the margin alongside the ARR.
B40: Colour convention
C41: Blue — a figure taken from a source, or an input you can change.
C42: Black — calculated on this sheet.
C43: Green — links to another sheet in this workbook.
C44: Yellow fill — fill this in with your own numbers.
C45: Grey / blank — not disclosed. Deliberately left empty.

Sheet McEasy vs Benchmark
A1: McEasy 2030 against Cartrack FY2019 — the investor argument
A2: Cartrack crossed USD111m subscription ARR in FY2019 with 960,798 subscribers. McEasy targets USD100.9m ARR in 2030 with ~950k vehicles. Read the per-vehicle block, not the margin block.
A4: Block 1 — margin comparison. This is the block that invites the attack.
A5: Metric | B5: McEasy 2030 | C5: Cartrack FY2019 | D5: Delta | E5: Comment
A6: ARR (USD m) | B6: ='McEasy Model'!J7/1000000 -> 100.9007 | C6: ='Karooooo Path'!C23 -> 110.9854 | D6: =IF(COUNT(B6,C6)=2,B6-C6,"") -> -10.084703 | E6: Within 9%. Cartrack's is subscription revenue, the closest disclosed analogue to ARR.
A7: Total revenue (USD m) | B7: ='McEasy Model'!J10/1000000 -> 101.89465 | C7: ='Karooooo Path'!C22 -> 123.55474 | D7: =IF(COUNT(B7,C7)=2,B7-C7,"") -> -21.660091 | E7: McEasy earns less total revenue at the same subscriber count — see the ARPU row below.
A8: Gross margin | B8: ='McEasy Model'!J34 -> 0.65882156 | D8: =IF(COUNT(B8,C8)=2,B8-C8,"") | E8: Cartrack did not disclose gross profit in FY2019. Karooooo's Cartrack segment runs 72% today against McEasy's 75.6% SaaS-only line — near-identical software unit economics.
A9: EBITDA margin | B9: ='McEasy Model'!J37 -> 0.52717598 | C9: ='Karooooo Path'!C32 -> 0.44981391 | D9: =IF(COUNT(B9,C9)=2,B9-C9,"") -> 0.077362073 | E9: THE headline gap: 7.7pp. Do not lead with this number. Block 2 explains why it is a denominator effect.
A10: Net margin | B10: ='McEasy Model'!J40 -> 0.32202887 | C10: ='Karooooo Path'!C31 -> 0.21326874 | D10: =IF(COUNT(B10,C10)=2,B10-C10,"") -> 0.10876013 | E10: 10.9pp gap, entirely attributable to lower depreciation per vehicle.
A11: Depreciation % of revenue | B11: ='McEasy Model'!J38 -> 0.11360255 | C11: ='Karooooo Path'!C32-'Karooooo Path'!C30 -> 0.15448691 | D11: =IF(COUNT(B11,C11)=2,B11-C11,"") -> -0.040884369 | E11: Cartrack's is EBITDA margin less operating margin. McEasy carries a lighter asset base.
A12: Capex % of revenue | B12: ='McEasy Model'!J39 -> 0.18649777 | C12: ='Karooooo Path'!C34 -> 0.29963963 | D12: =IF(COUNT(B12,C12)=2,B12-C12,"") -> -0.11314186 | E12: 11.4pp lighter. The single most important assumption in the whole plan.
A13: Recurring % of revenue | B13: ='McEasy Model'!J8/'McEasy Model'!J10 -> 0.82147645 | C13: ='Karooooo Path'!C35 -> 0.89826904 | D13: =IF(COUNT(B13,C13)=2,B13-C13,"") -> -0.07679259 | E13: 82.1% versus 89.8%. McEasy carries more low-margin spareparts revenue, which is exactly what drags the gross margin and flatters the EBITDA margin.
A15: Block 2 — per vehicle per year. THIS IS THE ARGUMENT.
A16: Metric | B16: McEasy 2030 | C16: Cartrack FY2019 | D16: Delta % | E16: Comment
A17: Vehicles / subscribers | B17: ='McEasy Model'!$B$44 -> 950000 | C17: ='Karooooo Path'!C19 -> 960798 | D17: =IF(AND(COUNT(B17,C17)=2,C17<>0),B17/C17-1,"") -> -0.011238575 | E17: 950,000 against 960,798 — 1.1% apart. Not approximately the same scale; the same scale.
A18: Revenue | B18: ='McEasy Model'!J10/'McEasy Model'!$B$44 -> 107.25753 | C18: =('Karooooo Path'!C22*1000000)/'Karooooo Path'!C19 -> 128.59596 | D18: =IF(AND(COUNT(B18,C18)=2,C18<>0),B18/C18-1,"") -> -0.16593393 | E18: McEasy earns ~17% less per vehicle, because it passes through less hardware revenue.
A19: SaaS / subscription revenue | B19: ='McEasy Model'!J8/'McEasy Model'!$B$44 -> 88.109535 | C19: =('Karooooo Path'!C23*1000000)/'Karooooo Path'!C19 -> 115.51377 | D19: =IF(AND(COUNT(B19,C19)=2,C19<>0),B19/C19-1,"") -> -0.23723784 | E19: ~24% less. McEasy is assuming LESS pricing power than the benchmark achieved, not more.
A20: EBITDA | B20: ='McEasy Model'!J22/'McEasy Model'!$B$44 -> 56.543594 | C20: =('Karooooo Path'!C25*1000000)/'Karooooo Path'!C19 -> 57.844253 | D20: =IF(AND(COUNT(B20,C20)=2,C20<>0),B20/C20-1,"") -> -0.022485538 | E20: 2.3% apart. The two businesses generate the same cash per vehicle. This single row answers the margin objection.
A21: Cash cost (revenue less EBITDA) | B21: =('McEasy Model'!J10-'McEasy Model'!J22)/'McEasy Model'!$B$44 -> 50.713937 | C21: =(('Karooooo Path'!C22*1000000)-('Karooooo Path'!C25*1000000))/'Karooooo Path'!C19 -> 70.751711 | D21: =IF(AND(COUNT(B21,C21)=2,C21<>0),B21/C21-1,"") -> -0.28321257 | E21: 28% lower. Defensible on Indonesian versus South African fully-loaded cost per head — but it needs a headcount plan behind it.
A22: Depreciation | B22: ='McEasy Model'!J23/'McEasy Model'!$B$44 -> 12.184729 | C22: =(('Karooooo Path'!C13-'Karooooo Path'!C11)/'Karooooo Path'!C6*1000000)/'Karooooo Path'!C19 -> 19.866394 | D22: =IF(AND(COUNT(B22,C22)=2,C22<>0),B22/C22-1,"") -> -0.38666631 | E22: 39% lower, and the direct cause of the net-margin gap.
A23: Capex | B23: ='McEasy Model'!J31/'McEasy Model'!$B$44 -> 20.00329 | C23: =('Karooooo Path'!C15/'Karooooo Path'!C6*1000000)/'Karooooo Path'!C19 -> 38.532447 | D23: =IF(AND(COUNT(B23,C23)=2,C23<>0),B23/C23-1,"") -> -0.48087153 | E23: 48% lower. This is the one claim an investor should test — see Block 3.
A24: Net profit | B24: ='McEasy Model'!J25/'McEasy Model'!$B$44 -> 34.540021 | C24: =('Karooooo Path'!C12/'Karooooo Path'!C6*1000000)/'Karooooo Path'!C19 -> 27.425499 | D24: =IF(AND(COUNT(B24,C24)=2,C24<>0),B24/C24-1,"") -> 0.25941267 | E24: 26% HIGHER, entirely explained by the lower depreciation above. One coherent story, not three unrelated stretches.
A25: ARPU — total revenue per month | B25: ='McEasy Model'!J10/'McEasy Model'!$B$44/12 -> 8.9381275 | C25: =('Karooooo Path'!C22*1000000)/'Karooooo Path'!C19/12 -> 10.71633 | D25: =IF(AND(COUNT(B25,C25)=2,C25<>0),B25/C25-1,"") -> -0.16593393 | E25: USD8.94 against USD10.72.
A26: ARPU — SaaS only per month | B26: ='McEasy Model'!J8/'McEasy Model'!$B$44/12 -> 7.3424612 | C26: =('Karooooo Path'!C23*1000000)/'Karooooo Path'!C19/12 -> 9.6261477 | D26: =IF(AND(COUNT(B26,C26)=2,C26<>0),B26/C26-1,"") -> -0.23723784 | E26: USD7.34 against USD9.63.
A28: Block 3 — the one remaining claim: cost per NEW INSTALL, not per base vehicle
A29: McEasy 2030 capex per NEW INSTALLATION | B29: ='McEasy Model'!J31/('McEasy Model'!$B$44-('McEasy Model'!$B$44*'McEasy Model'!I8/'McEasy Model'!J8)) -> 54.217886 | E29: Capex is spent on new units, not on the whole base. This is the correct denominator and the number to quote. Full derivation on the 'Capex Decomposition' sheet.
A30: Bottom-up bill of materials for one basic-tracker install | B30: $26 – $46 | E30: 4G Cat-1 tracker USD15-25 landed, installation labour USD8-15, SIM and logistics USD3-6. The model's budget sits ABOVE this — it carries headroom rather than being aggressive. That is the answer to the capex question.
A31: Cartrack FY2019 capex per net addition, as reported | B31: =('Karooooo Path'!C15/'Karooooo Path'!C6*1000000)/('Karooooo Path'!C19-'Karooooo Path'!B19) -> 176.7847 | E31: Not comparable as reported: the line is 'PP&E AND CONTRACT ASSETS' and bundles capitalised commissions with stolen-vehicle-recovery infrastructure — ground and air recovery teams, control rooms, recovery fleet. Strip 30-40% and it lands near USD106-124 per install.
A32: Supporting evidence and the counter-risks
A33: • | B33: Queclink, the listed device vendor: FY2025 revenue FELL 7.8% while gross margin compressed from 40.1% to 36.9% and operating margin collapsed from 13.4% to 5.4%. Streamax: revenue FELL 10.8%. A device maker losing pricing power is a device buyer gaining it. Both on 'At 100M (Today)'.
A34: • | B34: Your own accounts carry the strongest argument: Sparepart Solutions is USD18.2m of 2030 revenue at a 21.2% gross margin — pass-through hardware. A device the customer BUYS is cost of revenue, not capex. Cartrack subsidised and retained its devices, so its spend sat in PP&E. Say the flip side too: this relocates cost rather than removing it, which is why the blended gross margin is 65.9% against 75.6% SaaS-only — and why EBITDA per vehicle still matches.
A35: • | B35: Counter-risk one: on the per-install denominator the gap versus Cartrack as reported is about -69%, WIDER than the -48% a per-base-vehicle comparison implies. Concede this before an investor derives it, then point at the bill of materials.
A36: • | B36: Counter-risk two: at a blended dashcam install cost, only a single-digit percentage of new installs can be AI video units before this budget breaks. Check it against the product roadmap.
A37: • | B37: Counter-risk three: capex here is derived as the change in GROSS fixed assets, so it excludes device retirement and replacement. If churned devices are not recovered and reused, true capex per install is higher and this argument weakens.
A39: Block 4 — bull / base / bear, each anchored on a real comparable
A40: Scenario | B40: EBITDA margin | C40: EBITDA (USD m) | D40: Net (USD m) | E40: Anchor and implied enterprise value
A41: Bear — Microlise economics | B41: ='At 100M (Today)'!Q6 -> 0.1 | C41: =IFERROR(B41*'McEasy Model'!J10/1000000,"") -> 10.189465 | D41: =IFERROR('At 100M (Today)'!P6*'McEasy Model'!J10/1000000,"") -> -2.6313388 | E41: Microlise runs 10% adjusted EBITDA and a statutory operating loss at USD78m ARR, and trades at 0.39x sales. USD100m of ARR at these economics is worth about USD40m of enterprise value. This is the real downside and it is not theoretical.
A42: Base — Cartrack FY2019 economics | B42: ='Karooooo Path'!C32 -> 0.44981391 | C42: =IFERROR(B42*'McEasy Model'!J10/1000000,"") -> 45.833632 | D42: =IFERROR('Karooooo Path'!C31*'McEasy Model'!J10/1000000,"") -> 21.730945 | E42: 45.0% EBITDA and 21.3% net, valued on Quartix's 2.93x sales — a profitable, listed, modest-growth telematics business. The defensible ask: we match the best emerging-market comparable at the same scale.
A43: Bull — McEasy's own model | B43: ='McEasy Model'!J37 -> 0.52717598 | C43: =IFERROR(B43*'McEasy Model'!J10/1000000,"") -> 53.716414 | D43: =IFERROR('McEasy Model'!J40*'McEasy Model'!J10/1000000,"") -> 32.81302 | E43: 52.7% EBITDA and 32.2% net, valued on Karooooo's 5.70x sales. Requires the device-cost claim in Block 3 to hold AND the growth in the next sheet to be delivered.
A44: Implied enterprise value at the anchor's sales multiple (USD m) | B44: =IFERROR('Valuation Signals'!G11*'McEasy Model'!J10/1000000,"") -> 39.227562 | C44: =IFERROR('Valuation Signals'!G9*'McEasy Model'!J10/1000000,"") -> 298.86435 | D44: =IFERROR('Valuation Signals'!G5*'McEasy Model'!J10/1000000,"") -> 580.29554 | E44: Bear / base / bull, left to right. The spread is what an investor is actually underwriting — the ARR figure alone tells them almost nothing.
A46: Notes & definitions
A47: How to run the meeting: open on Block 2, not Block 1. 'We are targeting the same subscriber base as Cartrack at its USD100m milestone, at a LOWER price per vehicle, generating the same EBITDA per vehicle.' That is a matching claim, not a beating claim, and it is very hard to argue with.
A48: Then pre-empt the one real objection yourself by putting Block 3 up: 'the only place we differ is device cost per vehicle, and here is why an Indonesian device in 2030 costs half a South African device in 2019.' Volunteering your own weakest link buys enormous credibility.
A49: Everything in the McEasy column flows from one yellow cell on the 'McEasy Model' sheet — the 2030 vehicle count. Flex it live in the room: at 900,000 vehicles EBITDA per vehicle is USD59.68 (+3.2% versus Cartrack), at 950,000 it is USD56.54 (-2.2%) and at 1,000,000 it is USD53.72 (-7.1%). The conclusion holds across the WHOLE range you quoted — it does not depend on picking a favourable vehicle count, which is what makes it safe to demonstrate live.
A50: One reconciliation to tighten first: 900,000 vehicles implies USD9.43 per month, just above the USD8-9 band. The self-consistent combination is ~943k-1,061k vehicles at USD8.00-9.00. See the check rows on the 'McEasy Model' sheet.
A51: For the downside, go to 'Conservative Cases'. It re-bases the whole 2026-2030 path to USD90m and USD80m of 2030 revenue and shows that this argument survives a VOLUME miss — EBITDA per vehicle stays within 7% of Cartrack even at USD80m — but not a PRICE miss, which lands 36% below the benchmark. If an investor pushes on the downside, that is the distinction to draw.

Sheet Conservative Cases
A1: Conservative cases — 2030 revenue $10m and $20m below plan
A2: Re-based month by month from Jul-2026 off observed H1 actuals. Two drivers per revenue level, because a volume miss and a price miss produce opposite conclusions at the same revenue.
A4: Block 1 — why the path diverges from Jul-2026, not from plan
A5: Monthly ARR growth, H1-2026 actual | B5: 3.54% → 2.98% → 2.93% → 2.83% → 2.65% | G5: Decelerating through the half. These are reported actuals, not estimates.
A6: Average observed monthly ARR growth | B6: 0.029856262 | G6: Geometric mean, Jan to Jun 2026.
A7: Jun-2026 actual ARR | B7: 9501627.7 | G7: Last actual month in the model.
A8: Plan Dec-2026 exit ARR | B8: 14398706 | G8: The 2026 target.
A9: Growth the plan needs in Jul-2026 alone | B9: 0.12872671 | G9: A step-change from the observed ~2.7% to nearly 13% in a single month, then about 6% a month for the rest of the year. This is the assumption the conservative cases test.
A10: Dec-2026 exit ARR if observed momentum continues | B10: 11335944
A11: Gap to plan on that basis | B11: =B8/B6-1 -> 4.8226753e+08 | G11: Formula below.
A12: Plan ARR multiple, 2026 exit to 2030 exit | B12: 7.0076228 | G12: The plan's own compounding, applied to a lower starting point.
A13: Implied 2030 ARR at observed momentum | B13: 79438020 | G13: So the $80m case is approximately the CURRENT TRAJECTORY, not an arbitrary haircut, and $90m is a partial-recovery case. That is a far stronger way to present these.
A15: Block 2 — 2030 profit and loss by scenario
A16: USD, year to Dec-2030 | B16: Base — the plan | C16: $90m — fewer vehicles | D16: $90m — lower ARPU | E16: $80m — fewer vehicles | F16: $80m — lower ARPU | G16: Notes
A17: Growth haircut applied from Jul-2026 | B17: 1 | C17: 0.94186133 | D17: 0.94186133 | E17: 0.88682291 | F17: 0.88682291 | G17: One lever: the plan's own monthly ARR growth rates multiplied by h from Jul-2026, solved so FY2030 revenue hits the target.
A18: Total revenue | B18: 1.0189465e+08 | C18: 90000000 | D18: 90000000 | E18: 80000000 | F18: 80000000
A19: SaaS Solutions | B19: 83704058 | C19: 73933468 | D19: 73933468 | E19: 65719137 | F19: 65719137
A20: Spare Part Solutions | B20: 18190596 | C20: 16066532 | D20: 16066532 | E20: 14280863 | F20: 14280863
A21: Cost of revenue — SaaS | B21: 20428538 | C21: 18043852 | D21: 20428538 | E21: 16039010 | F21: 20428538
A22: Cost of revenue — Spare Part | B22: 14335721 | C22: 12661791 | D22: 12661791 | E22: 11254541 | F22: 11254541
A23: Logistic cost | B23: 286714.42 | C23: 286714.42 | D23: 286714.42 | E23: 286714.42 | F23: 286714.42
A24: Sales & marketing | B24: 3404155.4 | C24: 3404155.4 | D24: 3404155.4 | E24: 3404155.4 | F24: 3404155.4
A25: Operational expenses | B25: 9723111.1 | C25: 9723111.1 | D25: 9723111.1 | E25: 9723111.1 | F25: 9723111.1
A26: EBITDA | B26: 53716414 | C26: 45880377 | D26: 43495690 | E26: 39292468 | F26: 34902940
A27: Depreciation | B27: 11575492 | C27: 10851994 | D27: 11575492 | E27: 10227144 | F27: 11575492
A28: Tax & interest | B28: 9327901.5 | C28: 7753539.5 | D28: 7065542.3 | E28: 6433615.2 | F28: 5163535.3
A29: Net profit | B29: 32813020 | C29: 27274843 | D29: 24854656 | E29: 22631709 | F29: 18163913
A30: Capex | B30: 19003126 | C30: 16784165 | D30: 19003126 | E30: 14918722 | F30: 19003126
A31: Gross margin | B31: =IFERROR(((B18-B21-B22)/B18),"") -> 0.65882156 | C31: =IFERROR(((C18-C21-C22)/C18),"") -> 0.65882619 | D31: =IFERROR(((D18-D21-D22)/D18),"") -> 0.63232968 | E31: =IFERROR(((E18-E21-E22)/E18),"") -> 0.65883061 | F31: =IFERROR(((F18-F21-F22)/F18),"") -> 0.60396151
A32: EBITDA margin | B32: =IFERROR(B26/B18,"") -> 0.52717598 | C32: =IFERROR(C26/C18,"") -> 0.50978196 | D32: =IFERROR(D26/D18,"") -> 0.48328545 | E32: =IFERROR(E26/E18,"") -> 0.49115585 | F32: =IFERROR(F26/F18,"") -> 0.43628675
A33: Net margin | B33: =IFERROR(B29/B18,"") -> 0.32202887 | C33: =IFERROR(C29/C18,"") -> 0.30305381 | D33: =IFERROR(D29/D18,"") -> 0.27616285 | E33: =IFERROR(E29/E18,"") -> 0.28289636 | F33: =IFERROR(F29/F18,"") -> 0.22704891
A34: Capex % of revenue | B34: =IFERROR(B30/B18,"") -> 0.18649777 | C34: =IFERROR(C30/C18,"") -> 0.18649072 | D34: =IFERROR(D30/D18,"") -> 0.21114584 | E34: =IFERROR(E30/E18,"") -> 0.18648403 | F34: =IFERROR(F30/F18,"") -> 0.23753907
A35: Sparepart share of revenue (must hold constant) | B35: =IFERROR(B20/B18,"") -> 0.17852355 | C35: =IFERROR(C20/C18,"") -> 0.17851702 | D35: =IFERROR(D20/D18,"") -> 0.17851702 | E35: =IFERROR(E20/E18,"") -> 0.17851078 | F35: =IFERROR(F20/F18,"") -> 0.17851078 | G35: Grady's constraint. Holds at 17.85% in every scenario because the plan's own monthly revenue mix is preserved.
A37: Block 3 — the benchmark check. This is where the two drivers part company.
A38: Vehicles at Dec-2030 | B38: 950000 | C38: 830608.99 | D38: 950000 | E38: 731195.73 | F38: 950000
A39: Revenue per vehicle per month | B39: =IFERROR(B18/B38/12,"") -> 8.9381275 | C39: =IFERROR(C18/C38/12,"") -> 9.0295194 | D39: =IFERROR(D18/D38/12,"") -> 7.8947368 | E39: =IFERROR(E18/E38/12,"") -> 9.1174857 | F39: =IFERROR(F18/F38/12,"") -> 7.0175439 | G39: Vehicles are derived from exit ARR at constant ARR-per-vehicle, so slower growth mechanically lifts this ratio slightly in the volume cases — full-year revenue is measured against a smaller exit base. A definitional artefact, not a price rise.
A40: EBITDA per vehicle per year | B40: =IFERROR(B26/B38,"") -> 56.543594 | C40: =IFERROR(C26/C38,"") -> 55.237034 | D40: =IFERROR(D26/D38,"") -> 45.784937 | E40: =IFERROR(E26/E38,"") -> 53.737278 | F40: =IFERROR(F26/F38,"") -> 36.739937
A41: Cartrack FY2019 EBITDA per subscriber | B41: ='Karooooo Path'!C25*1000000/'Karooooo Path'!C19 -> 57.844253
A42: Gap to the benchmark | B42: =IFERROR(B40/$B$41-1,"") -> -0.022485538 | C42: =IFERROR(C40/$B$41-1,"") -> -0.045073087 | D42: =IFERROR(D40/$B$41-1,"") -> -0.20847906 | E42: =IFERROR(E40/$B$41-1,"") -> -0.071000572 | F42: =IFERROR(F40/$B$41-1,"") -> -0.36484724 | G42: THE FINDING: a volume miss leaves the Cartrack argument intact — EBITDA per vehicle stays within 7% even at $80m. A price miss destroys it, landing 36% below the benchmark you are presenting against. Same revenue, opposite conclusion.
A44: Block 4 — re-based path, 2026 to 2030
A45: Base — the plan | B45: 2026 | C45: 2027 | D45: 2028 | E45: 2029 | F45: 2030 | G45: Haircut h = 1.0000
A46: Revenue | B46: 12341977 | C46: 23768213 | D46: 40254794 | E46: 64141519 | F46: 1.0189465e+08
A47: EBITDA | B47: 1377091.8 | C47: 6383868.8 | D47: 16048954 | E47: 30182959 | F47: 53716414
A48: Depreciation | B48: 1743695.7 | C48: 3172634.9 | D48: 5021158.3 | E48: 7531606.3 | F48: 11575492
A49: Tax & interest | B49: 102616.01 | C49: 710807.28 | D49: 2441004.8 | E49: 5013881.4 | F49: 9327901.5
A50: Net profit | B50: -469219.95 | C50: 2500426.7 | D50: 8586791.1 | E50: 17637471 | F50: 32813020
A51: Capex | B51: 2971213.1 | C51: 5754535.8 | D51: 7003219.6 | E51: 11244892 | F51: 19003126
A52: Free cash flow (EBITDA less tax less capex) | B52: =B47-B49-B51 -> -1696737.3 | C52: =C47-C49-C51 -> -81474.278 | D52: =D47-D49-D51 -> 6604729.9 | E52: =E47-E49-E51 -> 13924185 | F52: =F47-F49-F51 -> 25385387
A53: Closing cash | B53: 3795656.1 | C53: 4378637.3 | D53: 12171358 | E53: 25098319 | F53: 42418799
A55: $90m — fewer vehicles | B55: 2026 | C55: 2027 | D55: 2028 | E55: 2029 | F55: 2030 | G55: Haircut h = 0.9419
A56: Revenue | B56: 12230941 | C56: 22744210 | D56: 37430117 | E56: 58158055 | F56: 90000000
A57: EBITDA | B57: 1302291.6 | C57: 5700572.1 | D57: 14164210 | E57: 26231473 | F57: 45880377
A58: Depreciation | B58: 1742106.8 | C58: 3138381.8 | D58: 4893832.9 | E58: 7214169.3 | F58: 10851994
A59: Tax & interest | B59: 94241.092 | C59: 567141.34 | D59: 2051999.9 | E59: 4209484.1 | F59: 7753539.5
A60: Net profit | B60: -534056.26 | C60: 1995049 | D60: 7218377.4 | E60: 14807820 | F60: 27274843
A61: Capex | B61: 2943460.2 | C61: 5508112.7 | D61: 6512545.7 | E61: 10194779 | F61: 16784165
A62: Free cash flow (EBITDA less tax less capex) | B62: =B57-B59-B61 -> -1735409.7 | C62: =C57-C59-C61 -> -374681.91 | D62: =D57-D59-D61 -> 5599664.6 | E62: =E57-E59-E61 -> 11827210 | F62: =F57-F59-F61 -> 21342673
A63: Closing cash | B63: 3747168.1 | C63: 3981253.7 | D63: 10708796 | E63: 21550659 | F63: 35694595
A65: $90m — lower ARPU | B65: 2026 | C65: 2027 | D65: 2028 | E65: 2029 | F65: 2030 | G65: Haircut h = 0.9419
A66: Revenue | B66: 12230941 | C66: 22744210 | D66: 37430117 | E66: 58158055 | F66: 90000000
A67: EBITDA | B67: 1279489.7 | C67: 5486132.9 | D67: 13584565 | E67: 25032487 | F67: 43495690
A68: Depreciation | B68: 1743695.7 | C68: 3172634.9 | D68: 5021158.3 | E68: 7531606.3 | F68: 11575492
A69: Tax & interest | B69: 91393.495 | C69: 512093.25 | D69: 1895511.8 | E69: 3873823.5 | F69: 7065542.3
A70: Net profit | B70: -555599.53 | C70: 1801404.8 | D70: 6667895 | E70: 13627058 | F70: 24854656
A71: Capex | B71: 2971213.1 | C71: 5754535.8 | D71: 7003219.6 | E71: 11244892 | F71: 19003126
A72: Free cash flow (EBITDA less tax less capex) | B72: =B67-B69-B71 -> -1783116.9 | C72: =C67-C69-C71 -> -780496.2 | D72: =D67-D69-D71 -> 4685833.8 | E72: =E67-E69-E71 -> 9913771.7 | F72: =F67-F69-F71 -> 17427022
A73: Closing cash | B73: 3699461 | C73: 3527732.3 | D73: 9341443.9 | E73: 18269868 | F73: 28498155
A75: $80m — fewer vehicles | B75: 2026 | C75: 2027 | D75: 2028 | E75: 2029 | F75: 2030 | G75: Haircut h = 0.8868
A76: Revenue | B76: 12127139 | C76: 21813970 | D76: 34933134 | E76: 52997410 | F76: 80000000
A77: EBITDA | B77: 1232363.3 | C77: 5079857.7 | D77: 12498073 | E77: 22823366 | F77: 39292468
A78: Depreciation | B78: 1740616.4 | C78: 3106937.4 | D78: 4779184 | E78: 6933951.5 | F78: 10227144
A79: Tax & interest | B79: 94478.441 | C79: 444542.35 | D79: 1708577.7 | E79: 3517125.1 | F79: 6433615.2
A80: Net profit | B80: -602731.58 | C80: 1528377.9 | D80: 6010311.5 | E80: 12372290 | F80: 22631709
A81: Capex | B81: 2917511.7 | C81: 5284201.5 | D81: 6078747.1 | E81: 9289169.8 | F81: 14918722
A82: Free cash flow (EBITDA less tax less capex) | B82: =B77-B79-B81 -> -1779626.9 | C82: =C77-C79-C81 -> -648886.18 | D82: =D77-D79-D81 -> 4710748.3 | E82: =E77-E79-E81 -> 10017071 | F82: =F77-F79-F81 -> 17940131
A83: Closing cash | B83: 3693774.9 | C83: 3603326.6 | D83: 9390415.2 | E83: 18435084 | F83: 29907156
A85: $80m — lower ARPU | B85: 2026 | C85: 2027 | D85: 2028 | E85: 2029 | F85: 2030 | G85: Haircut h = 0.8868
A86: Revenue | B86: 12127139 | C86: 21813970 | D86: 34933134 | E86: 52997410 | F86: 80000000
A87: EBITDA | B87: 1188245 | C87: 4670624 | D87: 11405987 | E87: 20590274 | F87: 34902940
A88: Depreciation | B88: 1743695.7 | C88: 3172634.9 | D88: 5021158.3 | E88: 7531606.3 | F88: 11575492
A89: Tax & interest | B89: 91432.513 | C89: 343337.1 | D89: 1413283.2 | E89: 2890538.6 | F89: 5163535.3
A90: Net profit | B90: -646883.23 | C90: 1154652 | D90: 4971545.9 | E90: 10168129 | F90: 18163913
A91: Capex | B91: 2971213.1 | C91: 5754535.8 | D91: 7003219.6 | E91: 11244892 | F91: 19003126
A92: Free cash flow (EBITDA less tax less capex) | B92: =B87-B89-B91 -> -1874400.6 | C92: =C87-C89-C91 -> -1427248.9 | D92: =D87-D89-D91 -> 2989484.6 | E92: =E87-E89-E91 -> 6454842.9 | F92: =F87-F89-F91 -> 10736279
A93: Closing cash | B93: 3599001.2 | C93: 2730190.1 | D93: 6796015 | E93: 12278456 | F93: 16546676
A95: Block 5 — the cash trough and the funding gap
A96: Cash and funding | B96: Base — the plan | C96: $90m — fewer vehicles | D96: $90m — lower ARPU | E96: $80m — fewer vehicles | F96: $80m — lower ARPU
A97: Minimum cash on the whole path | B97: 3285533.6 | C97: 3145445.4 | D97: 2950911.3 | E97: 2977126.1 | F97: 2511121.7
A98: Month it occurs | B98: 2027-05 | C98: 2027-05 | D98: 2027-07 | E98: 2027-07 | F98: 2027-09 | G98: Every scenario troughs in 2027 — including the plan itself. The pinch point is not 2030, it is the year after next.
A99: Buffer: 6 months of 2027 operating expenses | B99: 3815662.7
A100: Funding gap against that buffer | B100: =MAX(0,$B$99-B97) -> 530129.07 | C100: =MAX(0,$B$99-C97) -> 670217.26 | D100: =MAX(0,$B$99-D97) -> 864751.42 | E100: =MAX(0,$B$99-E97) -> 838536.6 | F100: =MAX(0,$B$99-F97) -> 1304541 | G100: Shown, not plugged. Note the plan itself is already about $0.5m short of a six-month buffer at its May-2027 trough, and the worst case is only about $1.3m short. The 2027 path is thin but not fragile — a modest facility covers every case here.
A102: Notes & definitions
A103: METHOD. Jan–Jun 2026 are reported actuals and are untouched. From Jul-2026 the plan's own monthly ARR growth rates are multiplied by a single constant h per scenario, solved so FY2030 revenue equals the target. Monthly revenue follows ARR using the plan's own revenue-to-ARR ratio for that month, which preserves seasonality and the revenue mix.
A104: WHAT FLEXES. Volume driver: vehicles fall, price holds, so cost of revenue and capex scale with revenue. ARPU driver: the vehicle count holds and price falls, so SaaS cost of revenue and capex are held in absolute terms — the devices are already bought — while spare-part cost of revenue scales with spare-part revenue at plan margin.
A105: WHAT IS HELD. Everything below gross profit — logistics, sales & marketing and operating expenses — is held at plan in every scenario. That is full operating deleverage with no assumed cost cuts, which is the conservative reading and the one an investor will credit.
A106: DEPRECIATION. Device life is 48 months, which the actuals support: the implied blended life over H1-2026 averages 47.7 months. Depreciation is carried on a delta basis — the plan's own figure plus the incremental 48-month cohort effect of the capex change — so base and ARPU cases tie to the plan exactly while the volume case picks up the capex reduction with the correct lag. The cohort reproduces reported accumulated depreciation at Jun-2026 to within 0.13%.
A107: CASH. Rolled monthly from the Jun-2026 actual balance as EBITDA less tax less capex less the change in working capital, with working capital scaled to trailing revenue. Non-modelled items are calibrated on the plan and carried into every scenario, so the base path reproduces the plan's cash at every year end to the cent. The 2026 equity raise is already in the Jun-2026 balance — paid-up capital reads $20,086,600 — so no further equity is assumed anywhere.
A108: THE HONEST CAVEAT. Margins fall only gently in the volume cases (52.7% to 49.1%) because operating expenses are just 9.5% of 2030 revenue. That shallow decline is a property of this model's very thin fixed-cost base, not a law of the business. A company carrying a normal fixed-cost load would be hurt considerably more by the same revenue miss.

Sheet Capex Decomposition
A1: Capex per vehicle — decomposed, because the headline gap is the wrong number
A2: Capex is spent on NEW installations, not on the whole base. On the correct denominator the gap is wider, not narrower — and that is fine, because the absolute cost per install is what matters and it is conservative.
A4: Block 1 — the denominator problem
A5: Basis | B5: McEasy 2030 | C5: Cartrack FY2019 | D5: Delta | E5: Why it matters
A6: Capex per vehicle in the BASE | B6: ='McEasy Model'!J31/'McEasy Model'!$B$44 -> 20.00329 | C6: =('Karooooo Path'!C15/'Karooooo Path'!C6*1000000)/'Karooooo Path'!C19 -> 38.532447 | D6: =IFERROR(B6/C6-1,"") -> -0.48087153 | E6: The figure originally shown. It divides a flow (a year's spend) by a stock (the whole installed base), so it is not a unit cost of anything. Do not lead with it.
A7: Net additions in the year | B7: =('McEasy Model'!$B$44-('McEasy Model'!$B$44*'McEasy Model'!I8/'McEasy Model'!J8)) -> 350495.51 | C7: =('Karooooo Path'!C19-'Karooooo Path'!B19) -> 209418 | E7: McEasy's 2029 vehicle count is NOT in the model. It is proxied here by scaling the 2030 count by the ratio of 2029 to 2030 SaaS revenue, i.e. assuming flat ARPU. Replace with the real ramp when you build one.
A8: Capex per NET ADDITION | B8: ='McEasy Model'!J31/('McEasy Model'!$B$44-('McEasy Model'!$B$44*'McEasy Model'!I8/'McEasy Model'!J8)) -> 54.217886 | C8: =('Karooooo Path'!C15/'Karooooo Path'!C6*1000000)/('Karooooo Path'!C19-'Karooooo Path'!B19) -> 176.7847 | D8: =IFERROR(B8/C8-1,"") -> -0.6933112 | E8: The economically correct denominator, and the gap is WIDER here. Concede this before an investor derives it. Then point at Block 2 — the absolute number is conservative.
A10: Block 2 — what one installation actually costs at 2026 prices
A11: Component | B11: Low (USD) | C11: High (USD) | E11: Source / note
A12: 4G Cat-1 basic tracker, volume, landed Indonesia | B12: 15 | C12: 25 | E12: Concox / Jimi IoT wholesale runs USD12-49 with high-volume pricing as low as USD5-12; Teltonika FMB920 is about EUR35 at retail. Replace with your own quotes.
A13: Installation labour, roughly one hour | B13: 8 | C13: 15 | E13: Indonesian technician, fully loaded. Materially below the South African equivalent.
A14: SIM activation, logistics, spares, wastage | B14: 3 | C14: 6 | E14: Estimate — refine from your own actuals.
A15: Bill of materials — one basic tracker install | B15: =SUM(B12:B14) -> 26 | C15: =SUM(C12:C14) -> 46 | E15: Compare against the per-net-add budget above.
A16: Headroom in the model's budget versus the high case | B16: =B8-C15 -> 8.2178861 | E16: Positive means the model is CONSERVATIVE per install, not aggressive. This is the single most useful sentence you can say on this topic.
A17: AI dashcam / video unit install, all-in | B17: 80 | C17: 200 | E17: Materially dearer than a basic tracker.
A18: Maximum dashcam share the budget supports | B18: =IFERROR(MAX(0,(B8-C15)/(AVERAGE(B17,C17)-C15)),"") -> 0.08742432 | E18: At a blended dashcam install cost, this is the share of new installs that can be video units before the capex budget breaks. CHECK THIS AGAINST THE PRODUCT ROADMAP — if video is a bigger part of the 2030 mix, capex is understated.
A20: Block 3 — RESOLVED. Cartrack's actual FY2019 device capex, from Note 5 of the Karooooo F-1
A21: Source: Karooooo Ltd Form F-1 (Mar-2021), Note 5 'Property, plant and equipment' FY2019 movement table, and Note 6 'Capitalized commission assets'. Figures in ZAR thousands as reported; the reconciliation below ties exactly.
A22: FY2019 line item (ZAR 000s) | B22: Amount | C22: % of cash-flow line | E22: Note
A23: Capitalised telematics devices — additions | B23: 353655 | C23: =B23/507151 -> 0.69733669 | E23: Note 5. The device AND its directly related installation costs, capitalised together and depreciated straight-line over the expected average contract life of 60 months. THIS is the figure a device-cost comparison should use.
A24: Other owned-asset additions | B24: 6836 | C24: =B24/507151 -> 0.01347922 | E24: Buildings, furniture and fixtures, leasehold improvements, plant and machinery — ZAR6.8m in total. Immaterial.
A25: Owned-asset additions = cash PP&E capex | B25: 360491 | C25: =B25/507151 -> 0.71081591 | E25: Note 5 total owned additions of ZAR360,491k. Right-of-use additions of ZAR74,364k (IT equipment, motor vehicles, property) are IFRS 16 lease recognitions, not cash capex, and are excluded here.
A26: Cash-flow line: PP&E AND CONTRACT ASSETS | B26: 507151 | C26: =B26/507151 -> 1 | E26: As reported in the FY2019 SENS. This is the figure that produced the USD176.77 per add.
A27: Residual = contract assets / capitalised commissions | B27: 146660 | C27: =B27/507151 -> 0.28918409 | E27: 28.9% of the line. Note 6 confirms a separate 'Capitalized sales commissions' asset — cost ZAR178,330k at Feb-2019. McEasy expenses commissions through S&M, so this has no McEasy equivalent at all.
A29: Restated on device capex only | B29: McEasy 2030 | C29: Cartrack FY2019 | D29: Gap | E29: Note
A30: Device + installation capex per NET ADDITION | B30: =B8 -> 54.217886 | C30: =B23/'Karooooo Path'!C6*1000/('Karooooo Path'!C19-'Karooooo Path'!B19) -> 123.26655 | D30: =IFERROR(B30/C30-1,"") -> -0.56015734 | E30: The gap to defend, correctly stated: device-and-install against device-and-install, per new unit. Down from -69% on the as-reported line.
A31: Device + installation capex per BASE vehicle | B31: ='McEasy Model'!J31/'McEasy Model'!$B$44 -> 20.00329 | C31: =B23/'Karooooo Path'!C6*1000/'Karooooo Path'!C19 -> 26.867493 | D31: =IFERROR(B31/C31-1,"") -> -0.25548356 | E31: On the base-vehicle view the restated gap is modest. This is the most favourable true framing available — and unlike the original -48% it is like-for-like.
A32: Cartrack device depreciation life | B32: 60 months | E32: Disclosed accounting policy: capitalised telematics devices are depreciated straight-line over the expected average contract life of 60 months, reduced where contracts are expected to be materially shorter. CHECK YOUR OWN ASSUMED DEVICE LIFE against this — if yours is longer, that explains part of the depreciation-per-vehicle gap and is a separate assumption to defend.
A34: Block 4 — an internal tension to reconcile before the meeting
A35: Metric | B35: McEasy 2030 | C35: Cartrack FY2019 | E35: Note
A36: Base growth in the year | B36: =IFERROR('McEasy Model'!$B$44/('McEasy Model'!$B$44*'McEasy Model'!I8/'McEasy Model'!J8)-1,"") -> 0.58464202 | C36: =IFERROR('Karooooo Path'!C19/'Karooooo Path'!B19-1,"") -> 0.27871117
A37: Capex as a multiple of depreciation | B37: =IFERROR('McEasy Model'!J31/'McEasy Model'!J23,"") -> 1.6416689 | C37: =IFERROR(('Karooooo Path'!C15/'Karooooo Path'!C6*1000000)/(('Karooooo Path'!C13-'Karooooo Path'!C11)/'Karooooo Path'!C6*1000000),"") -> 1.9395793 | E37: A faster-growing base should carry a HIGHER capex-to-depreciation multiple, because more of the spend is on units not yet depreciated. McEasy grows the base roughly twice as fast as Cartrack did, on a LOWER multiple. Either device life is assumed longer, capex is light, or the vehicle ramp is back-loaded. An investor building a device cohort model will find this.
A39: Block 5 — the justifications, ranked by how well they survive scrutiny
A40: You sell hardware; Cartrack subsidised it | B40: Tier 1 | E40: Sparepart Solutions is USD18.2m of 2030 revenue at a 21.2% gross margin — the signature of pass-through hardware at low markup. A device the customer BUYS is cost of revenue, not capex. Cartrack retained device ownership so its device spend sat in PP&E. Say the flip side yourself: this relocates cost rather than removing it, which is exactly why the blended gross margin is 65.9% against 75.6% SaaS-only, and exactly why EBITDA per vehicle still matches.
A41: Cartrack's line bundles things you do not capitalise — now proven, not asserted | B41: Tier 1 | E41: Note 5 of the Karooooo F-1 shows FY2019 capitalised telematics device additions of ZAR353,655k against a cash-flow line of ZAR507,151k. The ZAR146,660k residual (28.9%) is capitalised sales commissions, which Note 6 carries as a separate asset and which McEasy expenses through S&M. A further ZAR74,364k of right-of-use additions in the note are IFRS 16 lease recognitions, not cash capex. Restating device-for-device closes most of the gap.
A42: Hardware price deflation, 2019 to 2026 | B42: Tier 2 | E42: Listed device vendors are visibly losing pricing power. Queclink FY2025: revenue -7.8%, gross margin 40.1% to 36.9%, operating margin 13.4% to 5.4%. Streamax FY2025: revenue -10.8%. Both on the 'At 100M (Today)' sheet with sources.
A43: Installation labour and asset mix | B43: Tier 2 | E43: Indonesian install labour sits well below South African. Two-wheelers and light assets cost a fraction of a truck unit with CAN bus and video — Queclink discloses a dedicated two-wheeler terminal line precisely because Southeast Asia has that volume.
A44: "We are more capital-efficient operators" | B44: Do not use | E44: Unquantifiable, and it invites the auditor question instead of answering it. Every argument above is either in your own accounts or in a listed company's disclosure. Stay there.
A46: Notes & definitions
A47: What to say: 'our capex is USD54 per new installation against a USD26-46 bill of materials, so we are carrying headroom. Cartrack's USD177 is not comparable — it bundles capitalised commissions and stolen-vehicle-recovery infrastructure we do not operate.' That answers the question instead of defending a percentage.
A48: Four things still to collect: (1) your own year-by-year vehicle ramp, so the per-add figure stops being a constant-ARPU proxy; (2) 2026 volume quotes from Teltonika, Queclink and Howen landed in Jakarta, by device type; (3) your device-mix plan against the dashcam ceiling in Block 2; (4) your assumed device life and churned-device recovery and refurbishment rate, against Cartrack's disclosed 60 months. Item (1) on the old list — Cartrack's PP&E note split — is now obtained and sits in Block 3.
A49: Where to find it yourself: Karooooo Ltd Form F-1, SEC accession 0001104659-21-029334, document tm2034233-5_f1.htm. Note 5 is 'Property, plant and equipment' — the second and third tables are the FY2020 and FY2019 movement reconciliations, with additions by asset class. Note 6 is 'Capitalized commission assets'. The F-1 is the only English SEC filing carrying audited FY2019 notes, because it was filed for the April 2021 NASDAQ listing with two comparative years.

Sheet Growth Reality Check
A1: The assumption that is genuinely more aggressive than the benchmark
A2: It is not the margin. It is delivering a 66% ARR CAGR while turning EBITDA-positive in 2026 and raising no further equity. No company in this peer set has done both at once.
A4: What the plan requires versus what the benchmark delivered
A5: Company / plan | B5: Period | C5: ARR or revenue CAGR | D5: FCF margin | E5: Comment
A6: McEasy — required | B6: 2025-2030 | C6: ='McEasy Model'!$B$53 -> 0.66210063 | E6: ARR from USD7.95m to USD100.9m: a 12.7x increase in five years.
A7: Cartrack — realised | B7: FY2019-FY2026 | C7: =('Karooooo Path'!I24/'Karooooo Path'!C23)^(1/7)-1 -> 0.16605644 | D7: ='Karooooo Path'!I33 -> 0.14765468 | E7: Cartrack's MATURE phase, from USD111m to USD325m. Not the right comparison for McEasy's stage, but it is what the benchmark actually did after the milestone.
A8: Cartrack — at the milestone | B8: FY2019 | C8: ='Karooooo Path'!C8/'Karooooo Path'!B8-1 -> 0.27828123 | D8: ='Karooooo Path'!C33 -> 0.021563183 | E8: Revenue growth in the year it crossed USD100m ARR: 27.8%, with a 2.2% FCF margin. Fast growth and free cash flow did not coexist even here.
A9: Netradyne | B9: 2023-2024 | C9: 0.62 | E9: The only company in the set growing at McEasy's required rate. Private, USD1.3bn valuation, no disclosed profitability, venture-funded.
A10: Motive | B10: LTM Sep-2025 | C10: 0.28 | D10: -0.23 | E10: Grew to USD501m ARR and still burns 23% of revenue. Filed to IPO in Dec-2025 and remains unpriced. This is what funding hypergrowth looks like.
A11: Karooooo | B11: FY2026 | C11: 0.1997 | E11: 20% growth at a 42% EBITDA margin and positive free cash flow — the profitable-growth case, at a third of McEasy's required rate.
A12: Quartix | B12: FY2025 | C12: 0.123 | D12: 0.1252 | E12: Profitable and slow. 2.93x sales.
A13: Microlise | B13: FY2025 | C13: 0.057 | D13: 0.1127 | E13: Slow AND unprofitable. 0.39x sales.
A14: McEasy's required rate as a multiple of Cartrack's realised rate | C14: =IFERROR(C6/C7,"") -> 3.9872025 | E14: In fairness: 66% off a USD7.95m base is a very different proposition from 66% off USD100m, and Cartrack's own growth at USD8m of ARR is not disclosed. The honest framing is that McEasy needs Netradyne-class growth with Cartrack-class margins.
A16: Funding: the plan self-funds from 2026 onward
A17: Year | B17: Cash at year end (USD) | C17: EBITDA (USD) | D17: Paid-up capital (USD) | E17: Comment
A18: 2025 | B18: ='McEasy Model'!E29 -> 1915277.6 | C18: ='McEasy Model'!E22 -> -1604798.7 | D18: ='McEasy Model'!E30 -> 15655051 | E18: Thinnest point in the plan: cash of USD1.9m against a USD1.6m EBITDA loss — under twelve months of runway before the 2026 raise.
A19: 2026 | B19: ='McEasy Model'!F29 -> 3795656.1 | C19: ='McEasy Model'!F22 -> 1377091.8 | D19: ='McEasy Model'!F30 -> 20086600 | E19: Paid-up capital rises USD4.43m and EBITDA turns positive in the same year. Both have to happen; the plan has no slack if either slips.
A20: 2027 | B20: ='McEasy Model'!G29 -> 4378637.3 | C20: ='McEasy Model'!G22 -> 6383868.8 | D20: ='McEasy Model'!G30 -> 20086600 | E20: Last year of low cash. From here the model is self-funding.
A21: 2028 | B21: ='McEasy Model'!H29 -> 12171358 | C21: ='McEasy Model'!H22 -> 16048954 | D21: ='McEasy Model'!H30 -> 20086600
A22: 2029 | B22: ='McEasy Model'!I29 -> 25098319 | C22: ='McEasy Model'!I22 -> 30182959 | D22: ='McEasy Model'!I30 -> 20086600
A23: 2030 | B23: ='McEasy Model'!J29 -> 42418799 | C23: ='McEasy Model'!J22 -> 53716414 | D23: ='McEasy Model'!J30 -> 20086600 | E23: USD42.4m of cash and no equity raised since 2026.
A25: Notes & definitions
A26: The investor question this sheet exists to answer: 'you are asking me to believe you will grow four times faster than Cartrack did and reach better unit economics than Cartrack ever had, without raising again.' Blocks 2 and 3 of the benchmark sheet answer the unit-economics half. This sheet is where you should concede that the growth half is the genuine risk, and show the bear case is survivable.
A27: The single most useful thing you can add to the model before the meeting is a year-by-year vehicle and ARPU build. Without it, the 66% CAGR is an assertion; with it, it becomes a sales capacity and installation-throughput question that you can actually defend with an operating plan.

Sheet McEasy Model
A1: McEasy's own model, as supplied — read directly from the source file
A2: Blue = taken verbatim from 'McEasy model for claude reading.xlsx'. Yellow = the volume assumption Grady supplied in conversation, which is NOT in the model. Nothing on the benchmark sheets hardcodes a McEasy number; they all point here.
A4: Line item (USD) | B4: 2022 | C4: 2023 | D4: 2024 | E4: 2025 | F4: 2026 | G4: 2027 | H4: 2028 | I4: 2029 | J4: 2030
A5: Status per the model | B5: Actual | C5: Actual | D5: Actual | E5: Actual | F5: Projection | G5: Projection | H5: Projection | I5: Projection | J5: Projection
A6: Profit and loss, as modelled
A7: ARR | B7: 971426.11 | C7: 2454952.9 | D7: 4663990.4 | E7: 7954403.2 | F7: 14398706 | G7: 26164255 | H7: 41096544 | I7: 64090664 | J7: 1.009007e+08
A8: Revenue — SaaS Solutions | B8: 551706.33 | C8: 1700156.8 | D8: 3297397.3 | E8: 6059842.3 | F8: 10545545 | G8: 20361874 | H8: 33907054 | I8: 52822062 | J8: 83704058
A9: Revenue — Sparepart Solutions | B9: =B10-B8 -> 0 | C9: =C10-C8 -> 0 | D9: =D10-D8 -> 301146.1 | E9: =E10-E8 -> 1515014.6 | F9: =F10-F8 -> 1796432.7 | G9: =G10-G8 -> 3406338.5 | H9: =H10-H8 -> 6347739.5 | I9: =I10-I8 -> 11319457 | J9: =J10-J8 -> 18190596
A10: Total Revenue | B10: 551706.33 | C10: 1700156.8 | D10: 3598543.4 | E10: 7574856.9 | F10: 12341977 | G10: 23768213 | H10: 40254794 | I10: 64141519 | J10: 1.0189465e+08
A11: Total Cost of Revenue | B11: 160287.97 | C11: 400746.91 | D11: 1035087.4 | E11: 2814571.6 | F11: 4060835.7 | G11: 7918430 | H11: 13385958 | I11: 21781037 | J11: 34764259
A12: Total Gross Profit | B12: 391418.36 | C12: 1299409.9 | D12: 2563456 | E12: 4760285.4 | F12: 8281141.8 | G12: 15849783 | H12: 26868836 | I12: 42360481 | J12: 67130395
A13: Logistic Cost | B13: 0 | C13: 0 | D13: 6031.0455 | E13: 44517.615 | F13: 30248.4 | G13: 58942.469 | H13: 102331.29 | I13: 178563.17 | J13: 286714.42
A14: Sales & Marketing Costs | B14: 364088.49 | C14: 833858.49 | D14: 1140042.6 | E14: 1184089.2 | F14: 1249396.8 | G14: 1775645.9 | H14: 2233706.6 | I14: 2823461.8 | J14: 3404155.4
A15: Contribution Margin | B15: 27329.875 | C15: 465551.37 | D15: 1417382.4 | E15: 3531678.5 | F15: 7001496.7 | G15: 14015194 | H15: 24532798 | I15: 39358456 | J15: 63439525
A16: Personnel Expenses | B16: 764893.78 | C16: 1485357.2 | D16: 1972518.5 | E16: 2811910.9 | F16: 3101906.4 | G16: 4107765.9 | H16: 4537471.3 | I16: 4931047.2 | J16: 5351772.8
A17: General & Administrative Expenses | B17: 570530.78 | C17: 900014.43 | D17: 1265911.2 | E17: 1613489.9 | F17: 1870083 | G17: 2255305.6 | H17: 2459328.1 | I17: 2684125.7 | J17: 2850604.1
A18: Marketing Expenses | B18: 31846.695 | C18: 84200.177 | D18: 91445.796 | E18: 84482.067 | F18: 70842.281 | G18: 83600 | H18: 239380 | I18: 243349 | J18: 127516.45
A19: Technology Expenses | B19: 189333.2 | C19: 293221.56 | D19: 515230.31 | E19: 609794.29 | F19: 566381.76 | G19: 1170102.4 | H19: 1233112.7 | I19: 1302424 | J19: 1378666.4
A20: Other Expenses (Income) | B20: 40836.929 | C20: -17481.927 | D20: -15053.583 | E20: 16800.051 | F20: 15191.48 | G20: 14551.449 | H20: 14551.449 | I20: 14551.449 | J20: 14551.449
A21: Total Operational Expenses | B21: 1597441.4 | C21: 2745311.4 | D21: 3830052.3 | E21: 5136477.2 | F21: 5624404.9 | G21: 7631325.4 | H21: 8483843.6 | I21: 9175497.4 | J21: 9723111.1
... A25: Net Profit (Loss) | B25: -1791502.1 | C25: -2760503.3 | D25: -3266212.2 | E25: -2820272.9 | F25: -461538.23 | G25: 3135502.6 | H25: 9905019.3 | I25: 17611156 | J25: 32813020
A27: From the balance sheet
A28: Fixed assets, gross | C28: 1942180.3 | D28: 3009920.2 | E28: 5206461.8 | F28: 8177674.8 | G28: 13932211 | H28: 20935430 | I28: 32180322 | J28: 51183448
A29: Cash and cash equivalents | C29: 1418750.8 | D29: 3168339.1 | E29: 1915277.6 | F29: 3795656.1 | G29: 4378637.3 | H29: 12171358 | I29: 25098319 | J29: 42418799
A30: Paid-up capital | C30: 8030051.4 | D30: 12655051 | E30: 15655051 | F30: 20086600 | G30: 20086600 | H30: 20086600 | I30: 20086600 | J30: 20086600
A31: Capex (year-on-year change in gross fixed assets) | D31: =IF(COUNT(D28,C28)=2,D28-C28,"") -> 1067739.9 | E31: =IF(COUNT(E28,D28)=2,E28-D28,"") -> 2196541.5 | F31: =IF(COUNT(F28,E28)=2,F28-E28,"") -> 2971213.1 | G31: =IF(COUNT(G28,F28)=2,G28-F28,"") -> 5754535.8 | H31: =IF(COUNT(H28,G28)=2,H28-G28,"") -> 7003219.6 | I31: =IF(COUNT(I28,H28)=2,I28-H28,"") -> 11244892 | J31: =IF(COUNT(J28,I28)=2,J28-I28,"") -> 19003126
A33: Margins and ratios (calculated)
A34: Gross margin | B34: =IF(COUNT(B12,B10)=2,B12/B10,"") -> 0.70946868 | C34: =IF(COUNT(C12,C10)=2,C12/C10,"") -> 0.76428826 | D34: =IF(COUNT(D12,D10)=2,D12/D10,"") -> 0.71235934 | E34: =IF(COUNT(E12,E10)=2,E12/E10,"") -> 0.62843238 | F34: =IF(COUNT(F12,F10)=2,F12/F10,"") -> 0.67097366 | G34: =IF(COUNT(G12,G10)=2,G12/G10,"") -> 0.6668479 | H34: =IF(COUNT(H12,H10)=2,H12/H10,"") -> 0.66746922 | I34: =IF(COUNT(I12,I10)=2,I12/I10,"") -> 0.66042218 | J34: =IF(COUNT(J12,J10)=2,J12/J10,"") -> 0.65882156
A35: Contribution margin | B35: =IF(COUNT(B15,B10)=2,B15/B10,"") -> 0.049536998 | C35: =IF(COUNT(C15,C10)=2,C15/C10,"") -> 0.2738285 | D35: =IF(COUNT(D15,D10)=2,D15/D10,"") -> 0.39387669 | E35: =IF(COUNT(E15,E10)=2,E15/E10,"") -> 0.466237 | F35: =IF(COUNT(F15,F10)=2,F15/F10,"") -> 0.56729132 | G35: =IF(COUNT(G15,G10)=2,G15/G10,"") -> 0.58966126 | H35: =IF(COUNT(H15,H10)=2,H15/H10,"") -> 0.60943792 | I35: =IF(COUNT(I15,I10)=2,I15/I10,"") -> 0.61361903 | J35: =IF(COUNT(J15,J10)=2,J15/J10,"") -> 0.62259915
A36: Total operational expenses % of revenue | B36: =IF(COUNT(B21,B10)=2,B21/B10,"") -> 2.895456 | C36: =IF(COUNT(C21,C10)=2,C21/C10,"") -> 1.6147401 | D36: =IF(COUNT(D21,D10)=2,D21/D10,"") -> 1.064334 | E36: =IF(COUNT(E21,E10)=2,E21/E10,"") -> 0.67809561 | F36: =IF(COUNT(F21,F10)=2,F21/F10,"") -> 0.45571343 | G36: =IF(COUNT(G21,G10)=2,G21/G10,"") -> 0.32107275 | H36: =IF(COUNT(H21,H10)=2,H21/H10,"") -> 0.21075362 | I36: =IF(COUNT(I21,I10)=2,I21/I10,"") -> 0.14305083 | J36: =IF(COUNT(J21,J10)=2,J21/J10,"") -> 0.095423172
A37: EBITDA margin | B37: =IF(COUNT(B22,B10)=2,B22/B10,"") -> -2.845919 | C37: =IF(COUNT(C22,C10)=2,C22/C10,"") -> -1.3409117 | D37: =IF(COUNT(D22,D10)=2,D22/D10,"") -> -0.67045735 | E37: =IF(COUNT(E22,E10)=2,E22/E10,"") -> -0.21185861 | F37: =IF(COUNT(F22,F10)=2,F22/F10,"") -> 0.11157789 | G37: =IF(COUNT(G22,G10)=2,G22/G10,"") -> 0.26858851 | H37: =IF(COUNT(H22,H10)=2,H22/H10,"") -> 0.3986843 | I37: =IF(COUNT(I22,I10)=2,I22/I10,"") -> 0.4705682 | J37: =IF(COUNT(J22,J10)=2,J22/J10,"") -> 0.52717598
A38: Depreciation % of revenue | B38: =IF(COUNT(B23,B10)=2,B23/B10,"") -> 0.26218225 | C38: =IF(COUNT(C23,C10)=2,C23/C10,"") -> 0.24278535 | D38: =IF(COUNT(D23,D10)=2,D23/D10,"") -> 0.2090374 | E38: =IF(COUNT(E23,E10)=2,E23/E10,"") -> 0.14937028 | F38: =IF(COUNT(F23,F10)=2,F23/F10,"") -> 0.14128172 | G38: =IF(COUNT(G23,G10)=2,G23/G10,"") -> 0.13348227 | H38: =IF(COUNT(H23,H10)=2,H23/H10,"") -> 0.12473442 | I38: =IF(COUNT(I23,I10)=2,I23/I10,"") -> 0.1174217 | J38: =IF(COUNT(J23,J10)=2,J23/J10,"") -> 0.11360255
A39: Capex % of revenue | B39: =IF(COUNT(B31,B10)=2,B31/B10,"") | C39: =IF(COUNT(C31,C10)=2,C31/C10,"") | D39: =IF(COUNT(D31,D10)=2,D31/D10,"") -> 0.29671448 | E39: =IF(COUNT(E31,E10)=2,E31/E10,"") -> 0.28997795 | F39: =IF(COUNT(F31,F10)=2,F31/F10,"") -> 0.24074044 | G39: =IF(COUNT(G31,G10)=2,G31/G10,"") -> 0.24211058 | H39: =IF(COUNT(H31,H10)=2,H31/H10,"") -> 0.17397231 | I39: =IF(COUNT(I31,I10)=2,I31/I10,"") -> 0.17531378 | J39: =IF(COUNT(J31,J10)=2,J31/J10,"") -> 0.18649777
A40: Net margin | B40: =IF(COUNT(B25,B10)=2,B25/B10,"") -> -3.2472023 | C40: =IF(COUNT(C25,C10)=2,C25/C10,"") -> -1.6236757 | D40: =IF(COUNT(D25,D10)=2,D25/D10,"") -> -0.90764841 | E40: =IF(COUNT(E25,E10)=2,E25/E10,"") -> -0.37232029 | F40: =IF(COUNT(F25,F10)=2,F25/F10,"") -> -0.037395809 | G40: =IF(COUNT(G25,G10)=2,G25/G10,"") -> 0.13192 | H40: =IF(COUNT(H25,H10)=2,H25/H10,"") -> 0.24605813 | I40: =IF(COUNT(I25,I10)=2,I25/I10,"") -> 0.27456719 | J40: =IF(COUNT(J25,J10)=2,J25/J10,"") -> 0.32202887
A41: ARR growth year on year | C41: =IFERROR(C7/B7-1,"") -> 1.5271638 | D41: =IFERROR(D7/C7-1,"") -> 0.89982884 | E41: =IFERROR(E7/D7-1,"") -> 0.70549306 | F41: =IFERROR(F7/E7-1,"") -> 0.81015537 | G41: =IFERROR(G7/F7-1,"") -> 0.81712549 | H41: =IFERROR(H7/G7-1,"") -> 0.57071331 | I41: =IFERROR(I7/H7-1,"") -> 0.55951469 | J41: =IFERROR(J7/I7-1,"") -> 0.57434317
A43: Volume assumption — SUPPLIED BY GRADY, NOT PRESENT IN THE MODEL
A44: Vehicles at 2030 — central case | B44: 950000 | C44: Grady stated ~900k-1m vehicles at USD8-9 per vehicle per month for 2030. The two sheets in the model contain no subscriber, vehicle or ARPU driver at all. Every per-vehicle figure in this workbook flows from this single yellow cell — change it and the whole benchmark reflows. Turning this into a modelled year-by-year build is the highest-value fix to the model itself.
A45: Vehicles at 2030 — low case | B45: 900000
A46: Vehicles at 2030 — high case | B46: 1000000
A47: Implied total revenue per vehicle per month | B47: =IFERROR(J10/'McEasy Model'!$B$44/12,"") -> 8.9381275 | C47: Must land inside the USD8-9 band Grady stated for the total line.
A48: Implied SaaS revenue per vehicle per month | B48: =IFERROR(J8/'McEasy Model'!$B$44/12,"") -> 7.3424612 | C48: Must land inside the USD8-9 band Grady stated for the total line.
A49: Vehicles implied by USD9.00/month (top of the stated band) | B49: =IFERROR(J10/9/12,"") -> 943469.02 | C49: Reconciliation check: the USD8-9 band and the 900k-1m range are not quite consistent at the low end. 900,000 vehicles implies USD9.43/month, just above the quoted band. The internally consistent combination is roughly 943k-1,061k vehicles at USD8.00-9.00, i.e. the upper half of the vehicle range. Worth tightening before the meeting — it is exactly the arithmetic an investor will run.
A50: Vehicles implied by USD8.00/month (bottom of the stated band) | B50: =IFERROR(J10/8/12,"") -> 1061402.6
A52: The growth the plan requires
A53: Required ARR CAGR, 2025 to 2030 | B53: =IFERROR((J7/E7)^(1/5)-1,"") -> 0.66210063
A54: ARR multiple, 2025 to 2030 | B54: =IFERROR(J7/E7,"") -> 12.684886
A56: Notes & definitions
A57: Every blue figure on this sheet was read programmatically from Grady's model file at build time, not transcribed. Sparepart revenue is shown as Total Revenue less SaaS revenue, so the revenue lines are forced to reconcile.
A58: The model is internally consistent: the balance sheet balances in every year, and the change in total retained earnings equals P&L net profit in every year. The 'Previous / Current Earnings' split inside the equity block is a period-labelling quirk, not an articulation error.
A59: Capex is derived, not disclosed: it is the year-on-year change in GROSS fixed assets, which ignores disposals. If McEasy retires and replaces devices at scale, true gross capex is higher than shown and the device-cost argument on the benchmark sheet gets harder, not easier.

Sheet At 100M (Today)
A1: Who is at this size RIGHT NOW — FMS / telematics, revenue USD80-250m
A2: Same columns as 'Current Position' so the two read side by side. Native reporting currency is kept alongside USD so nothing is hidden inside an FX conversion.
A4: Company | B4: Listing / ownership | C4: Fiscal period | D4: Currency | E4: ARR (USD m) | F4: Distance from USD100m ARR | G4: Total revenue (USD m) | H4: Recurring revenue (USD m) | I4: Recurring % of revenue | J4: Revenue growth YoY | K4: Subscribers / units | L4: Employees | M4: Revenue per employee (USD k) | N4: Gross margin | O4: Operating margin | P4: Net margin | Q4: EBITDA margin | R4: FCF (USD m) | S4: FCF margin | T4: Confidence | U4: Notes
A5: Block A — subscription-FMS operators, revenue USD80-250m (the primary comparison)
A6: Microlise | B6: AIM: SAAS (listed UK) | C6: FY2025 (Dec-25) | D6: GBP | E6: =59.2*Assumptions!$B$13 -> 78.0848 | F6: =IF(COUNT(E6)=1,E6-Assumptions!$B$15,"") -> -21.9152 | G6: =84.03*Assumptions!$B$13 -> 110.83557 | H6: =58.8*Assumptions!$B$13 -> 77.5572 | I6: =IF(COUNT(H6,G6)=2,H6/G6,"") -> 0.69975009 | J6: 0.057 | L6: 615 | M6: =IF(COUNT(G6,L6)=2,G6*1000/L6,"") -> 180.22044 | N6: 0.6442937 | O6: -0.028799238 | P6: -0.02582411 | Q6: 0.1 | R6: =9.47*Assumptions!$B$13 -> 12.49093 | S6: =IF(COUNT(R6,G6)=2,R6/G6,"") -> 0.11269785 | T6: H | U6: The anchor of this sheet and the most uncomfortable row in the workbook. ARR GBP59.2m (+4.6%), 64% gross margin, 1.4% churn, 417 new customers — and a STATUTORY OPERATING LOSS. The 10% figure is adjusted EBITDA, down from 14%. Enterprise value is GBP32m against GBP84m of revenue: 0.39x sales. Headcount also reported as ~730 across UK, France, Australia and India before announced cuts.
A7: ORBCOMM | B7: Private (GI Partners, 2021 LBO) | C7: TTM to Sep-25 | D7: USD | F7: =IF(COUNT(E7)=1,E7-Assumptions!$B$15,"") | G7: 250 | I7: =IF(COUNT(H7,G7)=2,H7/G7,"") | L7: 878 | M7: =IF(COUNT(G7,L7)=2,G7*1000/L7,"") -> 284.73804 | S7: =IF(COUNT(R7,G7)=2,R7/G7,"") | T7: L | U7: Top of the band at ~USD250m revenue. Taken private in April 2021 at ~USD1.1bn including net debt. No margin, ARR or geographic disclosure since. Included for scale and the buyout multiple only.
A8: CalAmp | B8: Private (Lynrock Lake, post-Ch11) | C8: CY2024 | D8: USD | F8: =IF(COUNT(E8)=1,E8-Assumptions!$B$15,"") | G8: 197 | H8: 126.9 | I8: =IF(COUNT(H8,G8)=2,H8/G8,"") -> 0.64416244 | K8: 2700000 | L8: 644 | M8: =IF(COUNT(G8,L8)=2,G8*1000/L8,"") -> 305.90062 | Q8: 0.064467005 | S8: =IF(COUNT(R8,G8)=2,R8/G8,"") | T8: M | U8: The cautionary row. Reached ~USD200m revenue and 2.7m subscribers, then filed a pre-packaged Chapter 11 in June 2024 that wiped out USD230m of debt AND the public equity; delisted October 2024. EBITDA margin of 6.4% could not service the balance sheet. Headcount is as at Feb-2023, the last 10-K.
A9: Teletrac Navman | B9: Private (Respida Capital, Jun-2026) | C9: CY2026 | D9: USD | F9: =IF(COUNT(E9)=1,E9-Assumptions!$B$15,"") | G9: 168 | I9: =IF(COUNT(H9,G9)=2,H9/G9,"") | M9: =IF(COUNT(G9,L9)=2,G9*1000/L9,"") | S9: =IF(COUNT(R9,G9)=2,R9/G9,"") | T9: L | U9: The valuation row. Vontier sold the majority to Respida Capital, completing 30-Jun-2026 at a total transaction value of USD220m — roughly 1.3x revenue — with only ~USD80m of cash proceeds to Vontier. A strategic owner exiting a USD168m-revenue FMS business at about one and a third times sales.
A10: Netradyne | B10: Private (VC; USD1.3bn valuation) | C10: CY2024-25 | D10: USD | E10: 210 | F10: =IF(COUNT(E10)=1,E10-Assumptions!$B$15,"") -> 110 | I10: =IF(COUNT(H10,G10)=2,H10/G10,"") | J10: 0.62 | L10: 1000 | M10: =IF(COUNT(G10,L10)=2,G10*1000/L10,"") | S10: =IF(COUNT(R10,G10)=2,R10/G10,"") | T10: L | U10: Above the band and growing fastest here: ARR USD210m in 2024 from USD129.8m in 2023, +62%. Valued at USD1.3bn on the 2025 Series D, ~6.2x ARR. Single product family (AI video safety). No margin disclosure. US-weighted with a large India engineering base.
A12: Block B — hardware / device vendors. NOT ARR comparables: these are suppliers to companies like McEasy, shown to expose where the device margin pool sits
A13: Queclink | B13: SHE: 300590 (listed China) | C13: FY2025 (Dec-25) | D13: CNY | F13: =IF(COUNT(E13)=1,E13-Assumptions!$B$15,"") | G13: =891.1/Assumptions!$B$14 -> 123.98258 | I13: =IF(COUNT(H13,G13)=2,H13/G13,"") | J13: -0.078 | L13: 570 | M13: =IF(COUNT(G13,L13)=2,G13*1000/L13,"") -> 217.5133 | N13: 0.36939737 | O13: 0.054438335 | P13: 0.083671866 | R13: =45.79/Assumptions!$B$14 -> 6.3709599 | S13: =IF(COUNT(R13,G13)=2,R13/G13,"") -> 0.051385928 | T13: H | U13: Squarely in the band at ~USD124m revenue, and squarely a device business: 37% gross margin, and operating margin collapsed from 13.4% to 5.4% in one year on a 7.8% revenue decline. 94% of revenue is earned outside China. Discloses a two-wheeler terminal line — directly relevant to Indonesian fleet mix.
A14: Streamax | B14: SZ: 002970 (listed China) | C14: FY2025 (Dec-25) | D14: CNY | F14: =IF(COUNT(E14)=1,E14-Assumptions!$B$15,"") | G14: =2477/Assumptions!$B$14 -> 344.63568 | I14: =IF(COUNT(H14,G14)=2,H14/G14,"") | J14: -0.108 | L14: 2231 | M14: =IF(COUNT(G14,L14)=2,G14*1000/L14,"") -> 154.47587 | N14: 0.44852644 | O14: 0.15139281 | P14: 0.15462253 | R14: =294/Assumptions!$B$14 -> 40.905486 | S14: =IF(COUNT(R14,G14)=2,R14/G14,"") -> 0.11869197 | T14: H | U14: ABOVE the band at ~USD345m revenue — kept because it is the most Southeast-Asia-relevant listed player at any scale, with 65% overseas revenue and 5m+ vehicles. Note the shape: revenue FELL 10.8% while gross margin rose from 35.0% to 44.8% and net margin reached 15.5%. Deliberately traded volume for margin.
A16: Block C — below the band, but the closest business models to McEasy
A17: Quartix | B17: AIM: QTX (listed UK) | C17: FY2025 (Dec-25) | D17: GBP | E17: =37*Assumptions!$B$13 -> 48.803 | F17: =IF(COUNT(E17)=1,E17-Assumptions!$B$15,"") -> -51.197 | G17: =35.71*Assumptions!$B$13 -> 47.10149 | H17: =35.71*Assumptions!$B$13 -> 47.10149 | I17: =IF(COUNT(H17,G17)=2,H17/G17,"") -> 1 | J17: 0.123 | K17: 310701 | L17: 173 | M17: =IF(COUNT(G17,L17)=2,G17*1000/L17,"") -> 272.26295 | N17: 0.73172781 | O17: 0.24306917 | P17: 0.17866144 | R17: =4.47*Assumptions!$B$13 -> 5.89593 | S17: =IF(COUNT(R17,G17)=2,R17/G17,"") -> 0.12517502 | T17: H | U17: The purest SMB-subscription telematics comparable that exists, and profitable at half the target size: 73% gross margin, 24% operating margin, 18% net margin, 12.5% FCF margin on ~USD47m of revenue. 310,701 subscriptions across 31,040 customers. Proof that this model works well below USD100m — and that scale is not what creates margin. Headcount 173 is a third-party estimate.
A18: Fleetio | B18: Private (VC; USD1.5bn valuation) | C18: CY2025 | D18: USD | F18: =IF(COUNT(E18)=1,E18-Assumptions!$B$15,"") | G18: 58 | I18: =IF(COUNT(H18,G18)=2,H18/G18,"") | K18: 8500 | L18: 463 | M18: =IF(COUNT(G18,L18)=2,G18*1000/L18,"") -> 125.26998 | S18: =IF(COUNT(R18,G18)=2,R18/G18,"") | T18: L | U18: The valuation counterpoint to Teletrac Navman. Raised USD450m+ Series D in March 2025 and acquired Auto Integrate; combined business valued above USD1.5bn on roughly USD58m of revenue — about 26x sales, versus Teletrac's 1.3x. 8,500+ fleets, 8m+ vehicles serviced. Revenue is a third-party estimate and the weakest number on this sheet. Subscribers column is fleets, not vehicles.
A20: Notes & definitions
A21: Read this sheet against 'At 100M (Historic)'. Cartrack at USD111m ARR in FY2019 ran a 45% EBITDA margin and a 21% net margin. Microlise at USD78m ARR today runs a 10% ADJUSTED EBITDA margin and a statutory operating loss. Same revenue scale, same industry, opposite economics — the difference is the market and the pricing power, not the size.
A22: Recurring % of revenue is blank where recurring revenue is not disclosed. It is not zero. Quartix's recurring figure equals total revenue because it reports no separate hardware line, not because a split was assumed.
A23: Currency column matters. GBP figures are multiplied by the GBP/USD rate on 'Assumptions'; CNY figures are divided by the USD/CNY rate. Every USD cell here is a live formula over the native reported number, so changing an FX assumption reflows the whole sheet.
A24: Microlise margins are STATUTORY (gross 64.4%, operating -2.9%, net -2.6%) with the company's own adjusted EBITDA margin of 10% shown in the EBITDA column. Mixing statutory and adjusted in one row is deliberate: the gap between them is the point.
A25: Blocks B and C are labelled because they are not like-for-like. Block B sells devices to operators; Block C is below the size band. Neither should be averaged into Block A.

Sheet At 100M (Historic)
A1: Comparables — at the moment they crossed ~USD100m ARR
A2: This is the real benchmark for a 2030 target of USD100m ARR. Note how different these columns look from the 'Current Position' sheet — particularly free-cash-flow margin.
A4: Company | B4: Fiscal period at ~USD100m ARR | C4: Years from founding | D4: Recurring revenue (USD m) | E4: Total revenue (USD m) | F4: Revenue growth YoY | G4: Subscribers | H4: ARPU (USD per subscriber per month) | I4: Employees | J4: Gross margin | K4: Operating margin | L4: Net margin | M4: EBITDA margin | N4: Capex % of revenue | O4: FCF margin | P4: Home market % of revenue | Q4: Confidence | R4: Notes
A5: Karooooo (Cartrack) | B5: FY2019 (Feb-19) | C5: 15 | D5: ='Karooooo Path'!C23 -> 110.9854 | E5: ='Karooooo Path'!C22 -> 123.55474 | F5: =IF(COUNT('Karooooo Path'!C8,'Karooooo Path'!B8)=2,'Karooooo Path'!C8/'Karooooo Path'!B8-1,"") -> 0.27828123 | G5: ='Karooooo Path'!C19 -> 960798 | H5: ='Karooooo Path'!C39 -> 9.6261477 | K5: ='Karooooo Path'!C30 -> 0.29532699 | L5: ='Karooooo Path'!C31 -> 0.21326874 | M5: ='Karooooo Path'!C32 -> 0.44981391 | N5: ='Karooooo Path'!C34 -> 0.29963963 | O5: ='Karooooo Path'!C33 -> 0.021563183 | P5: ='Revenue by Country'!F5 -> 0.73596833 | Q5: H | R5: The benchmark row. 45% EBITDA margin and 21% net margin, but free cash flow was close to nil because capex ran at 30% of revenue — the hardware-subsidy model converts almost all EBITDA into installed devices. Gross margin was not disclosed in the FY2019 release.
A6: Ituran | B6: ~CY2007 | C6: 12 | E6: 114 | F6: 0.17 | G6: 407000 | I6: 800 | Q6: L | R6: Revenue annualised from Q2-2007 of USD29.2m. ~800 staff as at 2006, 407k subscribers in 2007. Pre-2008 disclosure is thin; margins not retrieved. Directional only.
A7: Powerfleet (via MiX Telematics) | B7: FY2014 (Mar-14) | C7: 18 | D7: 81 | E7: 126 | F7: 0.2 | G7: 448000 | M7: 0.215 | Q7: M | R7: MiX Telematics (merged into Powerfleet in 2024) is the only lineage in Powerfleet that organically crossed USD100m. Figures are FY2014 guidance at the midpoint: revenue ZAR1,270-1,300m, subscription ZAR825-833m, adjusted EBITDA ZAR270-280m. EBITDA margin of ~21.5% at this scale versus Cartrack's 45% — the clearest illustration that USD100m ARR says nothing about profitability.
A8: Motive (as KeepTruckin) | B8: ~CY2019 | C8: 6 | P8: 0.9 | Q8: L | R8: Crossed ~USD100m ARR around 2019 (55k+ customers as at Apr-2019; USD150m ARR by 2021). Raised a USD149m Series D in 2019. No margin or headcount disclosure exists for that year — the company was private and deeply loss-making. The fastest to USD100m in this set by a wide margin, and still unprofitable seven years later.
A9: Geotab | B9: ~CY2013 (est.) | C9: 13 | Q9: L | R9: No historical disclosure. Founded 2000; reached USD412m by 2021. Included for completeness only.
A10: Lytx | B10: ~CY2013 (est.) | C10: 15 | Q10: L | R10: No historical disclosure.
A11: Gurtam | B11: Not reached | Q11: H | R11: At USD37.3m revenue in 2025, Gurtam has never approached USD100m. It is the useful counter-example: a profitable, capital-light platform business that chose not to chase scale.
A13: Notes & definitions
A14: Blank cells are honest. For four of the seven companies the USD100m-ARR year predates any meaningful public disclosure. Cartrack FY2019 is the only fully-populated row, which is why it should be McEasy's primary north star and the rest are context.
A15: The pattern that matters: time-to-USD100m ranged from 6 years (Motive, venture-funded, unprofitable) to 18 years (MiX Telematics). EBITDA margin at that milestone ranged from ~21% (MiX) to 45% (Cartrack) to deeply negative (Motive). USD100m ARR is not one destination — it is at least three different businesses.
A16: Cartrack's ~2% FCF margin at USD100m ARR is the number to internalise. High EBITDA plus 30% capex-to-revenue equals no free cash. Any 2030 plan that assumes USD100m ARR funds itself needs to be tested against this row.

Sheet Current Position
A1: Comparables — current position
A2: Most recent reported full year for each company. All figures in USD millions. Karooooo cells are live links to the 'Karooooo Path' sheet.
A4: Company | B4: Listing / ownership | C4: Fiscal period | D4: ARR (USD m) | E4: Total revenue (USD m) | F4: Recurring revenue (USD m) | G4: Recurring % of revenue | H4: Revenue growth YoY | I4: Subscribers / connected assets | J4: Employees | K4: Revenue per employee (USD k) | L4: Gross margin | M4: Operating margin | N4: Net margin | O4: EBITDA margin | P4: FCF (USD m) | Q4: FCF margin | R4: Confidence | S4: Notes
A5: Karooooo (Cartrack) | B5: NASDAQ: KARO | C5: FY2026 (Feb-26) | D5: ='Karooooo Path'!I24 -> 325.31407 | E5: ='Karooooo Path'!I22 -> 344.15829 | F5: ='Karooooo Path'!I23 -> 304.27136 | G5: =IF(COUNT(F5,E5)=2,F5/E5,"") -> 0.88410294 | H5: =IF(COUNT('Karooooo Path'!I8,'Karooooo Path'!H8)=2,'Karooooo Path'!I8/'Karooooo Path'!H8-1,"") -> 0.19969345 | I5: ='Karooooo Path'!I19 -> 2662222 | J5: 5000 | K5: =IF(COUNT(E5,J5)=2,E5*1000/J5,"") -> 68.831658 | L5: ='Karooooo Path'!I29 -> 0.67968607 | M5: ='Karooooo Path'!I30 -> 0.25825881 | N5: ='Karooooo Path'!I31 -> 0.18452272 | O5: ='Karooooo Path'!I32 -> 0.41704691 | P5: ='Karooooo Path'!I26 -> 50.816583 | Q5: =IF(COUNT(P5,E5)=2,P5/E5,"") -> 0.14765468 | R5: H | S5: The only comparable that is simultaneously growing ARR ~20%+ in local currency, GAAP-profitable at an 18% net margin, and free-cash-flow positive. Employees are the one soft number. Dividend-paying.
A6: Ituran | B6: NASDAQ: ITRN | C6: FY2025 (Dec-25) | E6: 359 | F6: 265.7 | G6: =IF(COUNT(F6,E6)=2,F6/E6,"") -> 0.74011142 | H6: 0.07 | I6: 2630000 | K6: =IF(COUNT(E6,J6)=2,E6*1000/J6,"") | M6: 0.218 | N6: 0.16155989 | O6: 0.26796657 | Q6: =IF(COUNT(P6,E6)=2,P6/E6,"") | R6: H | S6: Closest profitability profile to Karooooo. 16% net margin, 27% EBITDA margin, record USD88.6m operating cash flow. Growth is only 7% — this is a mature, cash-returning business, not a growth story. Israel + Brazil = 78% of revenue.
A7: Powerfleet | B7: NASDAQ: AIOT | C7: FY2026 (Mar-26) | E7: 443.8 | F7: 359.8 | G7: =IF(COUNT(F7,E7)=2,F7/E7,"") -> 0.81072555 | H7: 0.22 | I7: 2600000 | K7: =IF(COUNT(E7,J7)=2,E7*1000/J7,"") | L7: 0.555 | M7: 0.044164038 | N7: -0.046417305 | O7: 0.219 | P7: -9.6 | Q7: =IF(COUNT(P7,E7)=2,P7/E7,"") -> -0.021631365 | R7: H | S7: Roll-up of I.D. Systems, Pointer, MiX Telematics and Fleet Complete. 22% revenue growth is largely acquired, not organic. Still GAAP loss-making with net debt of USD239m at 2.47x EBITDA. A warning about buying your way to scale.
A8: Motive | B8: Private; S-1 filed, NYSE: MTVE pending | C8: LTM to Sep-25 | D8: 501 | E8: 429 | F8: 416.1 | G8: =IF(COUNT(F8,E8)=2,F8/E8,"") -> 0.96993007 | H8: 0.21 | J8: 4508 | K8: =IF(COUNT(E8,J8)=2,E8*1000/J8,"") -> 95.164153 | L8: 0.7 | M8: -0.17 | N8: -0.42315918 | P8: -78.7 | Q8: =IF(COUNT(P8,E8)=2,P8/E8,"") -> -0.18344988 | R8: H | S8: ARR USD501m at 28% growth but burning cash: -23% FCF margin, USD138.5m net loss over nine months. IPO filed 23-Dec-2025, still unpriced as at Jul-2026. Net dollar retention 110% core / 126% large. 90% US revenue. 78% of staff are offshore.
A9: Geotab | B9: Private, bootstrapped | C9: CY2024 | E9: 681 | G9: =IF(COUNT(F9,E9)=2,F9/E9,"") | I9: 5000000 | J9: 2900 | K9: =IF(COUNT(E9,J9)=2,E9*1000/J9,"") -> 234.82759 | Q9: =IF(COUNT(P9,E9)=2,P9/E9,"") | R9: L | S9: Largest pure-play by subscriptions (5m+) and never took outside capital. Revenue is a third-party estimate. 2,900+ staff. No margin data exists publicly.
A10: Lytx | B10: Private (Permira) | C10: CY2025 | G10: =IF(COUNT(F10,E10)=2,F10/E10,"") | I10: 5500000 | J10: 1082 | K10: =IF(COUNT(E10,J10)=2,E10*1000/J10,"") | Q10: =IF(COUNT(P10,E10)=2,P10/E10,"") | R10: L | S10: Video-based driver safety specialist. Public revenue estimates span USD100-500m — too wide to be useful. Included for product-strategy context, not financial benchmarking.
A11: Gurtam | B11: Private | C11: CY2025 | E11: 37.3 | G11: =IF(COUNT(F11,E11)=2,F11/E11,"") | I11: 4000000 | J11: 339 | K11: =IF(COUNT(E11,J11)=2,E11*1000/J11,"") -> 110.0295 | Q11: =IF(COUNT(P11,E11)=2,P11/E11,"") | R11: L | S11: Platform/reseller model (Wialon), not a direct fleet operator. USD37.3m revenue on 339 staff implies ~USD110k revenue per employee — the highest here. Relevant as a capital-light alternative model, not as an ARR comparable.
A13: Notes & definitions
A14: ARR is only reported by Karooooo and Motive. Ituran, Powerfleet, Geotab, Lytx and Gurtam do not publish an ARR figure, so revenue is the only like-for-like top line across the set.
A15: Ituran operating margin is the Q4-2025 rate (21.8%) used as a full-year proxy; the full-year figure was not disclosed in the results release. Ituran FCF is blank: operating cash flow was USD88.6m but capex was not disclosed, so an FCF margin cannot be computed honestly.
A16: Powerfleet FCF is the sum of disclosed halves (-USD13.7m H1, +USD4.1m H2). Motive net margin uses the nine-month loss over nine-month revenue, since no full-year figure exists yet.
A17: Recurring % of revenue is blank wherever recurring revenue is not disclosed. It is not zero.

Sheet Valuation Signals
A1: What the market actually pays for an FMS business at this scale
A2: Among the three LISTED companies the spread is about 15x; across every data point here it is about 67x. The growth and margin columns are present so the spread is explained rather than asserted. Market data as at 10-Aug-2026.
A4: Company | B4: Type of data point | C4: Date | D4: Scale metric | E4: Scale metric (USD m) | F4: EV or valuation (USD m) | G4: Multiple of scale metric | H4: EV / EBITDA | I4: Growth at that point | J4: Profitability at that point | K4: Confidence | L4: What happened / why the multiple
A5: Karooooo | B5: Listed enterprise value | C5: 10-Aug-2026 | D5: Revenue | E5: ='Current Position'!$E$5 -> 344.15829 | F5: 1960 | G5: =IF(AND(COUNT(E5,F5)=2,E5<>0),F5/E5,"") -> 5.6950538 | H5: 21.62 | I5: 0.1997 | J5: 42% adj. EBITDA margin | K5: H | L5: THE upper anchor for a profitable operator: 5.5x sales and 21.6x EBITDA on USD344m of revenue growing 20% with a 42% EBITDA margin. This is what the market pays when growth AND margin are both present.
A6: Fleetio | B6: Private round (post-money) | C6: Mar-2025 | D6: Revenue | E6: 58 | F6: 1500 | G6: =IF(AND(COUNT(E6,F6)=2,E6<>0),F6/E6,"") -> 25.862069 | J6: n/d; loss-making | K6: L | L6: ~26x sales, the highest multiple here, on the weakest revenue figure here. Priced on growth and the Auto Integrate network effect, not on profit. Revenue is a third-party estimate, so treat the multiple as indicative of appetite rather than a precise number.
A7: Netradyne | B7: Private round (post-money) | C7: 2025 Series D | D7: ARR | E7: 210 | F7: 1300 | G7: =IF(AND(COUNT(E7,F7)=2,E7<>0),F7/E7,"") -> 6.1904762 | I7: 0.62 | J7: n/d | K7: L | L7: ~6.2x ARR on 62% ARR growth. The cleanest read on what fast growth is worth at this scale without disclosed profitability.
A8: ORBCOMM | B8: Take-private (LBO) | C8: Apr-2021 | D8: Revenue | E8: 248.5 | F8: 1100 | G8: =IF(AND(COUNT(E8,F8)=2,E8<>0),F8/E8,"") -> 4.4265594 | J8: n/d | K8: M | L8: ~4.4x sales including net debt, on FY2020 revenue of USD248.5m. A 2021 deal, struck in a materially cheaper rate environment than today's.
A9: Quartix | B9: Listed enterprise value | C9: 10-Aug-2026 | D9: Revenue | E9: ='At 100M (Today)'!$G$17 -> 47.10149 | F9: =104.74*Assumptions!$B$13 -> 138.15206 | G9: =IF(AND(COUNT(E9,F9)=2,E9<>0),F9/E9,"") -> 2.933072 | H9: 8.05 | I9: 0.123 | J9: 24% operating margin | K9: H | L9: 2.8x sales and 8.1x EBITDA. Profitable, high gross margin, but only 12% growth and sub-scale — so the market pays half of Karooooo's sales multiple and a third of its EBITDA multiple.
A10: Teletrac Navman | B10: Trade sale (strategic exit) | C10: Jun-2026 | D10: Revenue | E10: 168 | F10: 220 | G10: =IF(AND(COUNT(E10,F10)=2,E10<>0),F10/E10,"") -> 1.3095238 | J10: n/d | K10: M | L10: ~1.3x sales. Vontier, a strategic owner, chose to exit a USD168m-revenue FMS business for a USD220m total transaction value and only ~USD80m of cash. Scale bought no premium.
A11: Microlise | B11: Listed enterprise value | C11: 10-Aug-2026 | D11: Revenue | E11: ='At 100M (Today)'!$G$6 -> 110.83557 | F11: =32.35*Assumptions!$B$13 -> 42.66965 | G11: =IF(AND(COUNT(E11,F11)=2,E11<>0),F11/E11,"") -> 0.38498155 | H11: 4.29 | I11: 0.057 | J11: 10% adj. EBITDA; statutory operating loss | K11: H | L11: THE lower anchor and the most important row in the workbook. 0.39x sales. A GBP84m revenue business with a 64% gross margin carries an enterprise value of GBP32m — less than five months of revenue. Low growth plus a statutory loss equals near-zero enterprise value, whatever the ARR says.
A12: CalAmp | B12: Chapter 11 restructuring | C12: Jun-2024 | D12: Revenue | E12: 197 | F12: 0 | G12: =IF(AND(COUNT(E12,F12)=2,E12<>0),F12/E12,"") -> 0 | J12: 6.4% EBITDA margin | K12: H | L12: Equity value to zero. ~USD200m of revenue and 2.7m subscribers were not enough: a 6.4% EBITDA margin could not service the debt, USD230m was written off, lenders took the company and it delisted. The floor case for reaching this scale unprofitably.
A14: Dispersion
A15: Highest multiple — all data points | B15: =MAX(G5:G12) -> 25.862069 | C15: Fleetio, at about 26x. Priced on growth, and computed on the least reliable revenue figure in the table — treat it as evidence of appetite, not a precise multiple.
A16: Lowest multiple — all data points, excluding the zero | B16: =_xlfn.MINIFS(G5:G12,G5:G12,">0") -> 0.38498155 | C16: Microlise, at about 0.39x. CalAmp's zero is excluded so it does not swallow the range — but its equity really did go to nil, which is the true floor.
A17: Ratio between them | B17: =IFERROR(B15/B16,"") -> 67.177424 | C17: Mixes a venture round with a listed enterprise value, so read it as an outer bound.
A18: Highest multiple — listed companies only | B18: =MAX(G5,G9,G11) -> 5.6950538 | C18: Karooooo. The cleanest comparison: three public companies, same day, same methodology.
A19: Lowest multiple — listed companies only | B19: =MIN(G5,G9,G11) -> 0.38498155 | C19: Microlise.
A20: Ratio between them (listed only) | B20: =IFERROR(B18/B19,"") -> 14.793056 | C20: THE number to remember. Same industry, same day, same disclosure regime — and roughly a 15x difference in what one dollar of revenue is worth, driven by growth and margin alone.
A22: Notes & definitions
A23: Multiples are not like-for-like and are not meant to be. A listed enterprise value, a venture round post-money and a completed trade sale are three different things — the 'Type of data point' column says which is which, and they should not be averaged.
A24: The pattern that survives the caveats: at USD100-250m of revenue, an FMS business is worth roughly 0.4x sales if it is growing slowly at a thin margin, and roughly 5-6x sales if it is growing 20%+ at a fat margin. The revenue number itself explains almost none of the variance.
A25: For McEasy this reframes the 2030 target. USD100m ARR at Microlise-like economics would be worth roughly USD40m of enterprise value. The same USD100m ARR at Cartrack-like economics would be worth several hundred million. The goal should be specified as ARR AND margin, never ARR alone.

Sheet Revenue by Country
A1: Revenue mix by country / region
A2: Karooooo FY2019 and FY2025 are disclosed; FY2026 is rolled forward from disclosed regional growth rates. Powerfleet does not disclose geography in its results release.
A4: Company | B4: Fiscal period | C4: Region / country | D4: Currency | E4: Revenue (m) | F4: % of total (computed) | G4: Growth applied | H4: % of total (as disclosed) | I4: Confidence | J4: Note
A5: Karooooo (Cartrack) | B5: FY2019 (Feb-19) | C5: South Africa | D5: ZAR | E5: 1245.7 | F5: =IFERROR(E5/SUMIFS($E$5:$E$19,$A$5:$A$19,$A5,$B$5:$B$19,$B5),"") -> 0.73596833 | I5: H | J5: 73.6% of revenue — home market dominance at the USD100m-ARR milestone.
A6: Karooooo (Cartrack) | B6: FY2019 (Feb-19) | C6: Asia-Pacific & Middle East | D6: ZAR | E6: 179.7 | F6: =IFERROR(E6/SUMIFS($E$5:$E$19,$A$5:$A$19,$A6,$B$5:$B$19,$B6),"") -> 0.10616803 | I6: H | J6: Segment EBITDA only ZAR16m — Asia was barely profitable at this stage.
A7: Karooooo (Cartrack) | B7: FY2019 (Feb-19) | C7: Europe | D7: ZAR | E7: 147.6 | F7: =IFERROR(E7/SUMIFS($E$5:$E$19,$A$5:$A$19,$A7,$B$5:$B$19,$B7),"") -> 0.087203119 | I7: H
A8: Karooooo (Cartrack) | B8: FY2019 (Feb-19) | C8: Africa — other | D8: ZAR | E8: 115.6 | F8: =IFERROR(E8/SUMIFS($E$5:$E$19,$A$5:$A$19,$A8,$B$5:$B$19,$B8),"") -> 0.068297294 | I8: H
A9: Karooooo (Cartrack) | B9: FY2019 (Feb-19) | C9: USA | D9: ZAR | E9: 4 | F9: =IFERROR(E9/SUMIFS($E$5:$E$19,$A$5:$A$19,$A9,$B$5:$B$19,$B9),"") -> 0.0023632282 | I9: H | J9: Loss-making sub-scale entry.
A10: Karooooo (Cartrack) | B10: FY2025 (Feb-25) | C10: South Africa | D10: ZAR | E10: 3360 | F10: =IFERROR(E10/SUMIFS($E$5:$E$19,$A$5:$A$19,$A10,$B$5:$B$19,$B10),"") -> 0.73642222 | I10: H | J10: 73.7% — essentially unchanged from FY2019 six years later.
A11: Karooooo (Cartrack) | B11: FY2025 (Feb-25) | C11: Asia-Pacific, Middle East & USA | D11: ZAR | E11: 659.6 | F11: =IFERROR(E11/SUMIFS($E$5:$E$19,$A$5:$A$19,$A11,$B$5:$B$19,$B11),"") -> 0.14456669 | I11: H
A12: Karooooo (Cartrack) | B12: FY2025 (Feb-25) | C12: Europe | D12: ZAR | E12: 399.2 | F12: =IFERROR(E12/SUMIFS($E$5:$E$19,$A$5:$A$19,$A12,$B$5:$B$19,$B12),"") -> 0.087493973 | I12: H
A13: Karooooo (Cartrack) | B13: FY2025 (Feb-25) | C13: Africa — other | D13: ZAR | E13: 143.8 | F13: =IFERROR(E13/SUMIFS($E$5:$E$19,$A$5:$A$19,$A13,$B$5:$B$19,$B13),"") -> 0.031517117 | I13: H
A14: Queclink | B14: FY2025 (Dec-25) | C14: Outside China | D14: CNY | E14: 840.69 | F14: =IFERROR(E14/SUMIFS($E$5:$E$19,$A$5:$A$19,$A14,$B$5:$B$19,$B14),"") -> 0.94342947 | I14: H | J14: 94.3% of revenue earned outside its home market — the mirror image of Cartrack. A device vendor exports; an FMS operator does not.
A15: Queclink | B15: FY2025 (Dec-25) | C15: China | D15: CNY | E15: 50.41 | F15: =IFERROR(E15/SUMIFS($E$5:$E$19,$A$5:$A$19,$A15,$B$5:$B$19,$B15),"") -> 0.056570531 | I15: H | J15: 5.7%.
A16: Karooooo (Cartrack) | B16: FY2026E (Feb-26) | C16: South Africa | D16: ZAR | E16: =E10*(1+G16) -> 4032 | F16: =IFERROR(E16/SUMIFS($E$5:$E$19,$A$5:$A$19,$A16,$B$5:$B$19,$B16),"") -> 0.74172267 | G16: 0.2 | I16: M | J16: Disclosed: South Africa subscription revenue grew 20% in FY2026.
A17: Karooooo (Cartrack) | B17: FY2026E (Feb-26) | C17: Asia-Pacific, Middle East & USA | D17: ZAR | E17: =E11*(1+G17) -> 771.732 | F17: =IFERROR(E17/SUMIFS($E$5:$E$19,$A$5:$A$19,$A17,$B$5:$B$19,$B17),"") -> 0.14196704 | G17: 0.17 | I17: M | J17: Disclosed: Asia & Middle East subscription revenue grew 17% (20% constant currency).
A18: Karooooo (Cartrack) | B18: FY2026E (Feb-26) | C18: Europe | D18: ZAR | E18: =E12*(1+G18) -> 487.024 | F18: =IFERROR(E18/SUMIFS($E$5:$E$19,$A$5:$A$19,$A18,$B$5:$B$19,$B18),"") -> 0.089592446 | G18: 0.22 | I18: M | J18: Disclosed: Europe subscription revenue grew 22% (19% constant currency).
A19: Karooooo (Cartrack) | B19: FY2026E (Feb-26) | C19: Africa — other | D19: ZAR | E19: =E13*(1+G19) -> 145.238 | F19: =IFERROR(E19/SUMIFS($E$5:$E$19,$A$5:$A$19,$A19,$B$5:$B$19,$B19),"") -> 0.026717837 | G19: 0.01 | I19: M | J19: No revenue growth disclosed; 1% subscriber growth used as a proxy. Lowest-confidence line.
C21: FY2026E regional total (check) | E21: =SUM(E16:E19) -> 5435.994 | J21: Compare with reported group revenue below. A gap is expected: regional growth rates are for subscription revenue, applied here to total revenue.
C22: FY2026 reported group revenue | E22: ='Karooooo Path'!I8 -> 5479
C23: Estimate as % of reported | E23: =IFERROR(E21/E22,"") -> 0.99215076 | J23: Above ~97% means the roll-forward is a fair approximation of the true mix.
A25: Other comparables
A26: Ituran | B26: FY2025 (Dec-25) | C26: Israel | D26: USD | E26: =IFERROR(H26*'Current Position'!$E$6,"") -> 197.45 | F26: =IFERROR(H26,"") -> 0.55 | H26: 0.55 | I26: H | J26: Q4-2025 disclosed mix, used as the full-year proxy.
A27: Ituran | B27: FY2025 (Dec-25) | C27: Brazil | D27: USD | E27: =IFERROR(H27*'Current Position'!$E$6,"") -> 82.57 | F27: =IFERROR(H27,"") -> 0.23 | H27: 0.23 | I27: H | J27: Second home market; the LatAm stolen-vehicle-recovery engine.
A28: Ituran | B28: FY2025 (Dec-25) | C28: Rest of world | D28: USD | E28: =IFERROR(H28*'Current Position'!$E$6,"") -> 78.98 | F28: =IFERROR(H28,"") -> 0.22 | H28: 0.22 | I28: H | J28: Argentina, Mexico, USA, Colombia, Ecuador.
A29: Motive | B29: LTM to Sep-25 | C29: United States | D29: USD | E29: =IFERROR(H29*'Current Position'!$E$8,"") -> 386.1 | F29: =IFERROR(H29,"") -> 0.9 | H29: 0.9 | I29: M | J29: S-1 states approximately 90% US revenue.
A30: Motive | B30: LTM to Sep-25 | C30: International | D30: USD | E30: =IFERROR(H30*'Current Position'!$E$8,"") -> 42.9 | F30: =IFERROR(H30,"") -> 0.1 | H30: 0.1 | I30: M | J30: Canada and Mexico principally; not broken out.
A31: Streamax | B31: FY2025 (Dec-25) | C31: Overseas (ex-China) | D31: USD | E31: =IFERROR(H31*'At 100M (Today)'!$G$14,"") -> 224.01319 | F31: =IFERROR(H31,"") -> 0.65 | H31: 0.65 | I31: M | J31: Company states 65% overseas. Large Southeast Asian installed base; no country split published.
A32: Streamax | B32: FY2025 (Dec-25) | C32: China | D32: USD | E32: =IFERROR(H32*'At 100M (Today)'!$G$14,"") -> 120.62249 | F32: =IFERROR(H32,"") -> 0.35 | H32: 0.35 | I32: M | J32: Residual.
A33: Powerfleet | B33: FY2026 (Mar-26) | C33: n/d | I33: n/d | J33: n/d in the results release. Operates in North America, Israel, Europe, South Africa, Australia and Latin America following the MiX Telematics and Fleet Complete mergers. Geography is in the 10-K segment note only.
A34: Geotab | B34: CY2024 | C34: n/d | I34: n/d | J34: n/d. North-America-weighted; 55,000+ customers and 5m+ subscriptions globally.
A35: Lytx | B35: CY2025 | C35: n/d | I35: n/d | J35: n/d. North-America-weighted.
A36: Gurtam | B36: CY2025 | C36: n/d | I36: n/d | J36: n/d. Reseller network across CIS, Europe, Middle East, Africa, LatAm and Asia.
A37: Microlise | B37: FY2025 (Dec-25) | C37: n/d | I37: n/d | J37: n/d as a split. Operations in the UK, France, Australia and India serving 2,500+ clients; management states growth was broad-based across all geographies. The only mix it does disclose is channel: global OEM customers fell to 27% of revenue from 33%.
A38: Quartix | B38: FY2025 (Dec-25) | C38: n/d | I38: n/d | J38: n/d as percentages. Disclosed order of size only: UK largest, then France, then USA, then other European territories.
A39: CalAmp | B39: CY2024 | C39: n/d | I39: n/d | J39: n/d. Went private via Chapter 11 in June 2024 and stopped filing; the last 10-K geographic note predates the restructuring.
A40: Netradyne | B40: CY2025 | C40: n/d | I40: n/d | J40: n/d. US-weighted with a large India engineering base.
A41: ORBCOMM | B41: TTM Sep-25 | C41: n/d | I41: n/d | J41: n/d. Private since 2021.
A42: Teletrac Navman | B42: CY2026 | C42: n/d | I42: n/d | J42: n/d. Historically US, Australia, New Zealand and the UK.
A43: Fleetio | B43: CY2025 | C43: n/d | I43: n/d | J43: n/d. North-America-centred: USA, Canada and Mexico repair-shop network, with customers in 100+ countries.
A45: Cartrack subscribers by region (disclosed — highest-confidence geographic cut)
A46: Region | B46: FY2026 subscribers | C46: FY2025 subscribers | D46: Growth | E46: FY2026 share of base
A47: South Africa | B47: 2005888 | C47: 1736542 | D47: =IFERROR(B47/C47-1,"") -> 0.1551048 | E47: =IFERROR(B47/$B$51,"") -> 0.75346384
A48: Asia-Pacific & Middle East | B48: 335907 | C48: 273946 | D48: =IFERROR(B48/C48-1,"") -> 0.22617961 | E48: =IFERROR(B48/$B$51,"") -> 0.12617543
A49: Europe | B49: 228384 | C49: 200774 | D49: =IFERROR(B49/C49-1,"") -> 0.13751781 | E49: =IFERROR(B49/$B$51,"") -> 0.085786985
A50: Africa — other | B50: 92043 | C50: 90974 | D50: =IFERROR(B50/C50-1,"") -> 0.01175061 | E50: =IFERROR(B50/$B$51,"") -> 0.034573751
A51: Total | B51: =SUM(B47:B50) -> 2662222 | C51: =SUM(C47:C50) -> 2302236 | D51: =IFERROR(B51/C51-1,"") -> 0.15636364 | E51: =IFERROR(B51/$B$51,"") -> 1
A53: Notes & definitions
A54: The headline finding for McEasy: Cartrack's home market was 73.6% of revenue at USD100m ARR and is still ~74% at USD325m ARR. Geographic diversification did NOT fund the path from USD100m to USD325m — deepening penetration of the home market did. Southeast Asia is 12.6% of the subscriber base after roughly fifteen years of presence.
A55: Management explicitly flags that Southeast Asian ARPU (Indonesia, Philippines, Thailand) is materially below South African ARPU, and that a rising SEA mix will dilute group ARPU. This is the single most important structural warning in the dataset for an Indonesia-based company.

Sheet Revenue by Product
A1: Revenue mix by product line
A2: Only Karooooo, Powerfleet and Ituran disclose a usable split. Motive discloses recurring vs other but not by product. Geotab, Lytx and Gurtam disclose nothing.
A4: Company | B4: Fiscal period | C4: Revenue category / product line | D4: Currency | E4: Amount (m) | F4: % of company total | G4: Confidence | H4: Note
A5: Karooooo (Cartrack) | B5: FY2026 (Feb-26) | C5: Cartrack — subscription (SaaS telematics) | D5: ZAR | E5: 4831 | F5: =IFERROR(E5/SUMIFS($E$5:$E$26,$A$5:$A$26,$A5,$B$5:$B$26,$B5),"") -> 0.88173024 | G5: H | H5: Disclosed segment figure.
A6: Karooooo (Cartrack) | B6: FY2026 (Feb-26) | C6: Cartrack — hardware, installation & other | D6: ZAR | E6: 108 | F6: =IFERROR(E6/SUMIFS($E$5:$E$26,$A$5:$A$26,$A6,$B$5:$B$26,$B6),"") -> 0.019711626 | G6: M | H6: Cartrack total revenue ZAR4,939m less subscription ZAR4,831m.
A7: Karooooo (Cartrack) | B7: FY2026 (Feb-26) | C7: Karooooo Logistics — Delivery-as-a-Service | D7: ZAR | E7: 540 | F7: =IFERROR(E7/SUMIFS($E$5:$E$26,$A$5:$A$26,$A7,$B$5:$B$26,$B7),"") -> 0.098558131 | G7: H | H7: Disclosed segment. Gross margin only 31% vs 72% for Cartrack.
A8: Karooooo (Cartrack) | B8: FY2019 (Feb-19) | C8: Subscription (SaaS telematics) | D8: ZAR | E8: 1520.5 | F8: =IFERROR(E8/SUMIFS($E$5:$E$26,$A$5:$A$26,$A8,$B$5:$B$26,$B8),"") -> 0.89826904 | G8: H | H8: The USD100m-ARR vintage — subscription was already ~90% of revenue.
A9: Karooooo (Cartrack) | B9: FY2019 (Feb-19) | C9: Hardware, installation & other | D9: ZAR | E9: 172.2 | F9: =IFERROR(E9/SUMIFS($E$5:$E$26,$A$5:$A$26,$A9,$B$5:$B$26,$B9),"") -> 0.10173096 | G9: M | H9: Total revenue ZAR1,692.7m less subscription ZAR1,520.5m.
A10: Ituran | B10: FY2025 (Dec-25) | C10: Telematics services — subscription fees | D10: USD | E10: 265.7 | F10: =IFERROR(E10/SUMIFS($E$5:$E$26,$A$5:$A$26,$A10,$B$5:$B$26,$B10),"") -> 0.74011142 | G10: M | H10: Company disclosed a 74% / 26% services-versus-products split of USD359.0m.
A11: Ituran | B11: FY2025 (Dec-25) | C11: Products — hardware sales | D11: USD | E11: 93.3 | F11: =IFERROR(E11/SUMIFS($E$5:$E$26,$A$5:$A$26,$A11,$B$5:$B$26,$B11),"") -> 0.25988858 | G11: M | H11: 26% of USD359.0m.
A12: Powerfleet | B12: FY2026 (Mar-26) | C12: Services (recurring: SaaS + connectivity) | D12: USD | E12: 359.8 | F12: =IFERROR(E12/SUMIFS($E$5:$E$26,$A$5:$A$26,$A12,$B$5:$B$26,$B12),"") -> 0.81072555 | G12: H | H12: Grew 30% YoY.
A13: Powerfleet | B13: FY2026 (Mar-26) | C13: Products (hardware) | D13: USD | E13: 84 | F13: =IFERROR(E13/SUMIFS($E$5:$E$26,$A$5:$A$26,$A13,$B$5:$B$26,$B13),"") -> 0.18927445 | G13: H | H13: Declined slightly YoY — deliberate shift toward recurring.
A14: Motive | B14: LTM to Sep-25 | C14: Recurring subscription revenue | D14: USD | E14: 416.1 | F14: =IFERROR(E14/SUMIFS($E$5:$E$26,$A$5:$A$26,$A14,$B$5:$B$26,$B14),"") -> 0.96993007 | G14: M | H14: S-1 states recurring revenue is 97% of total; applied to LTM revenue of USD429m.
A15: Motive | B15: LTM to Sep-25 | C15: Other (services, hardware) | D15: USD | E15: 12.9 | F15: =IFERROR(E15/SUMIFS($E$5:$E$26,$A$5:$A$26,$A15,$B$5:$B$26,$B15),"") -> 0.03006993 | G15: M | H15: Residual 3%.
A16: Microlise | B16: FY2025 (Dec-25) | C16: Recurring revenue (subscription / SaaS) | D16: GBP | E16: 58.8 | F16: =IFERROR(E16/SUMIFS($E$5:$E$26,$A$5:$A$26,$A16,$B$5:$B$26,$B16),"") -> 0.7 | G16: H | H16: Grew 7.5%, of which direct customers +16%. 70% of revenue.
... A26: Queclink | B26: FY2025 (Dec-25) | C26: Two-wheeler smart terminal | D26: CNY | E26: 15.02 | F26: =IFERROR(E26/SUMIFS($E$5:$E$26,$A$5:$A$26,$A26,$B$5:$B$26,$B26),"") -> 0.016855572 | G26: H | H26: 1.7%. Directly relevant to Indonesian two-wheeler fleets.
A27: Geotab | B27: CY2024 | C27: n/d | G27: n/d | H27: Not disclosed. Private, bootstrapped. Third-party revenue estimate only; no product-line split published.
A28: Lytx | B28: CY2025 | C28: n/d | G28: n/d | H28: Not disclosed. Permira-owned; video-based safety is the core line but no split published.
A29: Gurtam | B29: CY2025 | C29: n/d | G29: n/d | H29: Not disclosed. Reseller/channel model on the Wialon platform; revenue is platform licence fees, not end-customer subscriptions.
A30: Streamax | B30: FY2025 (Dec-25) | C30: n/d | G30: n/d | H30: Not disclosed at this granularity. AI video / AIoT fleet-safety hardware and platform; 65% of revenue is overseas.
A31: ORBCOMM | B31: TTM Sep-25 | C31: n/d | G31: n/d | H31: Not disclosed. Private since the 2021 GI Partners buyout.
A32: Teletrac Navman | B32: CY2026 | C32: n/d | G32: n/d | H32: Not disclosed. Was never separately segment-reported inside Vontier.
A33: Netradyne | B33: CY2025 | C33: n/d | G33: n/d | H33: Not disclosed. Single product family (AI video safety, Driveri); ARR is effectively all of revenue.
A34: Fleetio | B34: CY2025 | C34: n/d | G34: n/d | H34: Not disclosed. Fleet maintenance SaaS plus the acquired Auto Integrate maintenance-authorisation network.
A36: Notes & definitions
A37: The pattern to take away: every profitable comparable is 74–98% recurring revenue, and the hardware line is flat-to-shrinking by design. Powerfleet's product revenue fell in absolute terms while services grew 30%.
A38: Karooooo's Delivery-as-a-Service line is a cautionary case: 10% of revenue at a 31% gross margin against 72% for the core telematics SaaS. Adjacent logistics services dilute the multiple even when they grow faster.

Sheet Karooooo Path
A1: Cartrack / Karooooo — full trajectory, FY2019 to FY2026
A2: The single most useful table in this workbook: Cartrack crossed ~USD100m subscription ARR in FY2019 and is at USD325m ARR today. This is the actual path, not the destination.
A4: Metric | B4: FY2018 | C4: FY2019 | D4: FY2020 | E4: FY2022 | F4: FY2023 | G4: FY2024 | H4: FY2025 | I4: FY2026
A5: Year ended | B5: Feb-2018 | C5: Feb-2019 | D5: Feb-2020 | E5: Feb-2022 | F5: Feb-2023 | G5: Feb-2024 | H5: Feb-2025 | I5: Feb-2026
A6: USD/ZAR average rate applied | B6: =Assumptions!$B$5 -> 12.9 | C6: =Assumptions!$B$6 -> 13.7 | D6: =Assumptions!$B$7 -> 14.6 | E6: =Assumptions!$B$8 -> 14.9 | F6: =Assumptions!$B$9 -> 17.4 | G6: =Assumptions!$B$10 -> 18.7 | H6: =Assumptions!$B$11 -> 18.63 | I6: =Assumptions!$B$12 -> 15.92
A7: As reported (ZAR millions)
A8: Total revenue | B8: 1324.2 | C8: 1692.7 | D8: 1946 | E8: 2746 | F8: 3507 | G8: 4206 | H8: 4567 | I8: 5479
A9: Subscription revenue | B9: 1165.5 | C9: 1520.5 | D9: 1888 | H9: 4068 | I9: 4844
A10: Gross profit | E10: 1824 | F10: 2272 | G10: 2691 | H10: 3203 | I10: 3724
A11: Operating profit | B11: 434.3 | C11: 499.9 | E11: 699.1 | F11: 881.9 | G11: 1043 | H11: 1312 | I11: 1415
A12: Profit for the year | B12: 310.5 | C12: 361 | E12: 450 | F12: 597.2 | G12: 738.2 | H12: 937 | I12: 1011
A13: EBITDA / adjusted EBITDA | B13: 650.8 | C13: 761.4 | H13: 1973 | I13: 2285
A14: Cash generated from operations | B14: 467.8 | C14: 543.7 | H14: 1933 | I14: 1967
A15: Capex (PP&E + contract assets) | B15: 420.1 | C15: 507.2 | H15: 1022 | I15: 1158
A16: Free cash flow (operating cash flow less capex) | B16: =IF(COUNT(B14,B15)=2,B14-B15,"") -> 47.7 | C16: =IF(COUNT(C14,C15)=2,C14-C15,"") -> 36.5 | D16: =IF(COUNT(D14,D15)=2,D14-D15,"") | E16: =IF(COUNT(E14,E15)=2,E14-E15,"") | F16: =IF(COUNT(F14,F15)=2,F14-F15,"") | G16: =IF(COUNT(G14,G15)=2,G14-G15,"") | H16: =IF(COUNT(H14,H15)=2,H14-H15,"") -> 911 | I16: =IF(COUNT(I14,I15)=2,I14-I15,"") -> 809
A17: Company-reported "adjusted free cash flow" | H17: 425 | I17: 809
A18: Cartrack SaaS ARR (ZAR m) | H18: 4384 | I18: 5179
A19: Subscribers (period end) | B19: 751380 | C19: 960798 | D19: 1126515 | H19: 2302236 | I19: 2662222
A21: Converted to USD millions (at the average rate in row 6)
A22: Total revenue | B22: =IF(COUNT(B8,B6)=2,B8/B6,"") -> 102.65116 | C22: =IF(COUNT(C8,C6)=2,C8/C6,"") -> 123.55474 | D22: =IF(COUNT(D8,D6)=2,D8/D6,"") -> 133.28767 | E22: =IF(COUNT(E8,E6)=2,E8/E6,"") -> 184.2953 | F22: =IF(COUNT(F8,F6)=2,F8/F6,"") -> 201.55172 | G22: =IF(COUNT(G8,G6)=2,G8/G6,"") -> 224.91979 | H22: =IF(COUNT(H8,H6)=2,H8/H6,"") -> 245.14224 | I22: =IF(COUNT(I8,I6)=2,I8/I6,"") -> 344.15829
A23: Subscription revenue | B23: =IF(COUNT(B9,B6)=2,B9/B6,"") -> 90.348837 | C23: =IF(COUNT(C9,C6)=2,C9/C6,"") -> 110.9854 | D23: =IF(COUNT(D9,D6)=2,D9/D6,"") -> 129.31507 | E23: =IF(COUNT(E9,E6)=2,E9/E6,"") | F23: =IF(COUNT(F9,F6)=2,F9/F6,"") | G23: =IF(COUNT(G9,G6)=2,G9/G6,"") | H23: =IF(COUNT(H9,H6)=2,H9/H6,"") -> 218.35749 | I23: =IF(COUNT(I9,I6)=2,I9/I6,"") -> 304.27136
A24: Cartrack SaaS ARR | B24: =IF(COUNT(B18,B6)=2,B18/B6,"") | C24: =IF(COUNT(C18,C6)=2,C18/C6,"") | D24: =IF(COUNT(D18,D6)=2,D18/D6,"") | E24: =IF(COUNT(E18,E6)=2,E18/E6,"") | F24: =IF(COUNT(F18,F6)=2,F18/F6,"") | G24: =IF(COUNT(G18,G6)=2,G18/G6,"") | H24: =IF(COUNT(H18,H6)=2,H18/H6,"") -> 235.31938 | I24: =IF(COUNT(I18,I6)=2,I18/I6,"") -> 325.31407
A25: EBITDA / adjusted EBITDA | B25: =IF(COUNT(B13,B6)=2,B13/B6,"") -> 50.449612 | C25: =IF(COUNT(C13,C6)=2,C13/C6,"") -> 55.576642 | D25: =IF(COUNT(D13,D6)=2,D13/D6,"") | E25: =IF(COUNT(E13,E6)=2,E13/E6,"") | F25: =IF(COUNT(F13,F6)=2,F13/F6,"") | G25: =IF(COUNT(G13,G6)=2,G13/G6,"") | H25: =IF(COUNT(H13,H6)=2,H13/H6,"") -> 105.90446 | I25: =IF(COUNT(I13,I6)=2,I13/I6,"") -> 143.53015
A26: Free cash flow (OCF less capex) | B26: =IF(COUNT(B16,B6)=2,B16/B6,"") -> 3.6976744 | C26: =IF(COUNT(C16,C6)=2,C16/C6,"") -> 2.6642336 | D26: =IF(COUNT(D16,D6)=2,D16/D6,"") | E26: =IF(COUNT(E16,E6)=2,E16/E6,"") | F26: =IF(COUNT(F16,F6)=2,F16/F6,"") | G26: =IF(COUNT(G16,G6)=2,G16/G6,"") | H26: =IF(COUNT(H16,H6)=2,H16/H6,"") -> 48.899624 | I26: =IF(COUNT(I16,I6)=2,I16/I6,"") -> 50.816583
A28: Margins
A29: Gross margin | B29: =IF(COUNT(B10,B8)=2,B10/B8,"") | C29: =IF(COUNT(C10,C8)=2,C10/C8,"") | D29: =IF(COUNT(D10,D8)=2,D10/D8,"") | E29: =IF(COUNT(E10,E8)=2,E10/E8,"") -> 0.66423889 | F29: =IF(COUNT(F10,F8)=2,F10/F8,"") -> 0.64784716 | G29: =IF(COUNT(G10,G8)=2,G10/G8,"") -> 0.63980029 | H29: =IF(COUNT(H10,H8)=2,H10/H8,"") -> 0.70133567 | I29: =IF(COUNT(I10,I8)=2,I10/I8,"") -> 0.67968607
A30: Operating margin | B30: =IF(COUNT(B11,B8)=2,B11/B8,"") -> 0.32797161 | C30: =IF(COUNT(C11,C8)=2,C11/C8,"") -> 0.29532699 | D30: =IF(COUNT(D11,D8)=2,D11/D8,"") | E30: =IF(COUNT(E11,E8)=2,E11/E8,"") -> 0.25458849 | F30: =IF(COUNT(F11,F8)=2,F11/F8,"") -> 0.25146849 | G30: =IF(COUNT(G11,G8)=2,G11/G8,"") -> 0.24797908 | H30: =IF(COUNT(H11,H8)=2,H11/H8,"") -> 0.2872783 | I30: =IF(COUNT(I11,I8)=2,I11/I8,"") -> 0.25825881
A31: Net margin | B31: =IF(COUNT(B12,B8)=2,B12/B8,"") -> 0.2344812 | C31: =IF(COUNT(C12,C8)=2,C12/C8,"") -> 0.21326874 | D31: =IF(COUNT(D12,D8)=2,D12/D8,"") | E31: =IF(COUNT(E12,E8)=2,E12/E8,"") -> 0.16387473 | F31: =IF(COUNT(F12,F8)=2,F12/F8,"") -> 0.170288 | G31: =IF(COUNT(G12,G8)=2,G12/G8,"") -> 0.17551117 | H31: =IF(COUNT(H12,H8)=2,H12/H8,"") -> 0.20516751 | I31: =IF(COUNT(I12,I8)=2,I12/I8,"") -> 0.18452272
A32: EBITDA margin | B32: =IF(COUNT(B13,B8)=2,B13/B8,"") -> 0.49146655 | C32: =IF(COUNT(C13,C8)=2,C13/C8,"") -> 0.44981391 | D32: =IF(COUNT(D13,D8)=2,D13/D8,"") | E32: =IF(COUNT(E13,E8)=2,E13/E8,"") | F32: =IF(COUNT(F13,F8)=2,F13/F8,"") | G32: =IF(COUNT(G13,G8)=2,G13/G8,"") | H32: =IF(COUNT(H13,H8)=2,H13/H8,"") -> 0.43201226 | I32: =IF(COUNT(I13,I8)=2,I13/I8,"") -> 0.41704691
A33: Free-cash-flow margin | B33: =IF(COUNT(B16,B8)=2,B16/B8,"") -> 0.036021749 | C33: =IF(COUNT(C16,C8)=2,C16/C8,"") -> 0.021563183 | D33: =IF(COUNT(D16,D8)=2,D16/D8,"") | E33: =IF(COUNT(E16,E8)=2,E16/E8,"") | F33: =IF(COUNT(F16,F8)=2,F16/F8,"") | G33: =IF(COUNT(G16,G8)=2,G16/G8,"") | H33: =IF(COUNT(H16,H8)=2,H16/H8,"") -> 0.19947449 | I33: =IF(COUNT(I16,I8)=2,I16/I8,"") -> 0.14765468
A34: Capex as % of revenue | B34: =IF(COUNT(B15,B8)=2,B15/B8,"") -> 0.31724815 | C34: =IF(COUNT(C15,C8)=2,C15/C8,"") -> 0.29963963 | D34: =IF(COUNT(D15,D8)=2,D15/D8,"") | E34: =IF(COUNT(E15,E8)=2,E15/E8,"") | F34: =IF(COUNT(F15,F8)=2,F15/F8,"") | G34: =IF(COUNT(G15,G8)=2,G15/G8,"") | H34: =IF(COUNT(H15,H8)=2,H15/H8,"") -> 0.22377929 | I34: =IF(COUNT(I15,I8)=2,I15/I8,"") -> 0.21135244
A35: Subscription revenue as % of total | B35: =IF(COUNT(B9,B8)=2,B9/B8,"") -> 0.88015406 | C35: =IF(COUNT(C9,C8)=2,C9/C8,"") -> 0.89826904 | D35: =IF(COUNT(D9,D8)=2,D9/D8,"") -> 0.97019527 | E35: =IF(COUNT(E9,E8)=2,E9/E8,"") | F35: =IF(COUNT(F9,F8)=2,F9/F8,"") | G35: =IF(COUNT(G9,G8)=2,G9/G8,"") | H35: =IF(COUNT(H9,H8)=2,H9/H8,"") -> 0.8907379 | I35: =IF(COUNT(I9,I8)=2,I9/I8,"") -> 0.88410294
A37: Unit economics
A38: Revenue per subscriber (USD per year) | B38: =IF(COUNT(B22,B19)=2,B22*1000000/B19,"") -> 136.61684 | C38: =IF(COUNT(C22,C19)=2,C22*1000000/C19,"") -> 128.59596 | D38: =IF(COUNT(D22,D19)=2,D22*1000000/D19,"") -> 118.31859 | E38: =IF(COUNT(E22,E19)=2,E22*1000000/E19,"") | F38: =IF(COUNT(F22,F19)=2,F22*1000000/F19,"") | G38: =IF(COUNT(G22,G19)=2,G22*1000000/G19,"") | H38: =IF(COUNT(H22,H19)=2,H22*1000000/H19,"") -> 106.48007 | I38: =IF(COUNT(I22,I19)=2,I22*1000000/I19,"") -> 129.27483
A39: Subscription revenue per subscriber (USD per month) | B39: =IF(COUNT(B23,B19)=2,B23*1000000/B19/12,"") -> 10.020322 | C39: =IF(COUNT(C23,C19)=2,C23*1000000/C19/12,"") -> 9.6261477 | D39: =IF(COUNT(D23,D19)=2,D23*1000000/D19/12,"") -> 9.5660117 | E39: =IF(COUNT(E23,E19)=2,E23*1000000/E19/12,"") | F39: =IF(COUNT(F23,F19)=2,F23*1000000/F19/12,"") | G39: =IF(COUNT(G23,G19)=2,G23*1000000/G19/12,"") | H39: =IF(COUNT(H23,H19)=2,H23*1000000/H19/12,"") -> 7.9038193 | I39: =IF(COUNT(I23,I19)=2,I23*1000000/I19/12,"") -> 9.5243546
A40: Net subscriber additions in the year | C40: =IF(COUNT(C19,B19)=2,C19-B19,"") -> 209418 | D40: =IF(COUNT(D19,C19)=2,D19-C19,"") -> 165717 | E40: =IF(COUNT(E19,D19)=2,E19-D19,"") | F40: =IF(COUNT(F19,E19)=2,F19-E19,"") | G40: =IF(COUNT(G19,F19)=2,G19-F19,"") | H40: =IF(COUNT(H19,G19)=2,H19-G19,"") | I40: =IF(COUNT(I19,H19)=2,I19-H19,"") -> 359986
A42: Notes & definitions
A43: FY2021 (year ended Feb-2021) is deliberately blank — it was not retrieved from a primary source. FY2020 total revenue is derived: subscription revenue of ZAR1,888m was disclosed as 97% of total. FY2018 is included to show the crossing: subscription revenue went from USD90m to USD111m.
A44: Karooooo Ltd. was interposed above Cartrack Holdings Ltd. ahead of the April 2021 NASDAQ listing. FY2019 and FY2020 are Cartrack Holdings (JSE-listed); FY2022 onward are Karooooo Ltd. The operating business is continuous, but the reporting entity and accounting basis are not identical.
A45: Gross profit is blank for FY2018-FY2020 because Cartrack Holdings reported under a cost classification that did not disclose it. The FY2019 SENS release also gave segment EBITDA rather than segment operating profit.
A46: Read the FY2019 column as the closest available analogue to McEasy at a USD100m ARR milestone.

Sheet McEasy Benchmark
A1: McEasy — what USD100m ARR by 2030 actually requires
A2: Yellow cells are for you to fill in. Everything else is calculated from the comparables.
A4: Your inputs
A5: McEasy ARR today (USD m) | B5: 15 | C5: Replace with your actual figure. 15.0 is a placeholder so the formulas below show a worked example.
A6: Base year | B6: 2026 | C6: Calendar year the ARR above refers to.
A7: Target ARR (USD m) | B7: =Assumptions!$B$15 -> 100 | C7: From the Assumptions sheet.
A8: Target year | B8: =Assumptions!$B$16 -> 2030 | C8: From the Assumptions sheet.
A10: What that implies
A11: Years to target | B11: =B8-B6 -> 4
A12: ARR multiple required | B12: =IFERROR(B7/B5,"") -> 6.6666667
A13: Required compound annual ARR growth | B13: =IFERROR((B7/B5)^(1/B11)-1,"") -> 0.60685684
A14: Cartrack's actual ARR CAGR, FY2019 to FY2026 (USD) | B14: =('Karooooo Path'!I24/'Karooooo Path'!C23)^(1/7)-1 -> 0.16605644 | C14: Cartrack went from ~USD111m to USD325m over seven years. If your required CAGR above is far higher than this, you are not planning a Cartrack trajectory — you are planning a Motive one, which needs venture capital and tolerates losses.
A16: Benchmark: what Cartrack looked like at ~USD100m ARR (FY2019)
A17: Subscription revenue (USD m) | B17: ='Karooooo Path'!C23 -> 110.9854
A18: Subscribers | B18: ='Karooooo Path'!C19 -> 960798
A19: ARPU (USD per subscriber per month) | B19: ='Karooooo Path'!C39 -> 9.6261477 | C19: The number McEasy should stress-test hardest. Indonesian ARPU is structurally below this.
A20: EBITDA margin | B20: ='Karooooo Path'!C32 -> 0.44981391
A21: Operating margin | B21: ='Karooooo Path'!C30 -> 0.29532699
A22: Net margin | B22: ='Karooooo Path'!C31 -> 0.21326874
A23: Capex as % of revenue | B23: ='Karooooo Path'!C34 -> 0.29963963 | C23: Devices, installation and contract assets. This is what eats the EBITDA.
A24: Free-cash-flow margin | B24: ='Karooooo Path'!C33 -> 0.021563183 | C24: Near zero. USD100m ARR did not make Cartrack self-funding.
A25: Home market share of revenue | B25: ='Revenue by Country'!F5 -> 0.73596833 | C25: Cartrack reached USD100m ARR on the back of one market, not many.
A27: Reality check — the same metrics for companies actually at this scale today
A28: Metric | B28: Cartrack FY2019 (at USD111m ARR) | C28: Microlise FY2025 (USD78m ARR) | D28: Quartix FY2025 (USD49m ARR) | E28: Karooooo FY2026 (USD325m ARR)
A29: ARR or subscription revenue (USD m) | B29: ='Karooooo Path'!C23 -> 110.9854 | C29: ='At 100M (Today)'!E6 -> 78.0848 | D29: ='At 100M (Today)'!E17 -> 48.803 | E29: ='Karooooo Path'!I24 -> 325.31407
A30: Total revenue (USD m) | B30: ='Karooooo Path'!C22 -> 123.55474 | C30: ='At 100M (Today)'!G6 -> 110.83557 | D30: ='At 100M (Today)'!G17 -> 47.10149 | E30: ='Karooooo Path'!I22 -> 344.15829
A31: Revenue growth YoY | B31: ='Karooooo Path'!C8/'Karooooo Path'!B8-1 -> 0.27828123 | C31: ='At 100M (Today)'!J6 -> 0.057 | D31: ='At 100M (Today)'!J17 -> 0.123 | E31: ='Current Position'!H5 -> 0.19969345
A32: Gross margin | C32: ='At 100M (Today)'!N6 -> 0.6442937 | D32: ='At 100M (Today)'!N17 -> 0.73172781 | E32: ='Karooooo Path'!I29 -> 0.67968607
A33: Operating margin (statutory) | B33: ='Karooooo Path'!C30 -> 0.29532699 | C33: ='At 100M (Today)'!O6 -> -0.028799238 | D33: ='At 100M (Today)'!O17 -> 0.24306917 | E33: ='Karooooo Path'!I30 -> 0.25825881
A34: Net margin (statutory) | B34: ='Karooooo Path'!C31 -> 0.21326874 | C34: ='At 100M (Today)'!P6 -> -0.02582411 | D34: ='At 100M (Today)'!P17 -> 0.17866144 | E34: ='Karooooo Path'!I31 -> 0.18452272
A35: EBITDA margin | B35: ='Karooooo Path'!C32 -> 0.44981391 | C35: ='At 100M (Today)'!Q6 -> 0.1 | E35: ='Karooooo Path'!I32 -> 0.41704691
A36: Free-cash-flow margin | B36: ='Karooooo Path'!C33 -> 0.021563183 | C36: ='At 100M (Today)'!S6 -> 0.11269785 | D36: ='At 100M (Today)'!S17 -> 0.12517502 | E36: ='Karooooo Path'!I33 -> 0.14765468
A37: ARPU (USD per subscriber per month) | B37: ='Karooooo Path'!C39 -> 9.6261477 | D37: =IFERROR('At 100M (Today)'!E17*1000000/'At 100M (Today)'!K17/12,"") -> 13.089487 | E37: ='Karooooo Path'!I39 -> 9.5243546
A38: Employees | C38: ='At 100M (Today)'!L6 -> 615 | D38: ='At 100M (Today)'!L17 -> 173 | E38: ='Current Position'!J5 -> 5000
A39: Revenue per employee (USD k) | C39: ='At 100M (Today)'!M6 -> 180.22044 | D39: ='At 100M (Today)'!M17 -> 272.26295 | E39: ='Current Position'!K5 -> 68.831658
A40: Enterprise value / sales | C40: ='Valuation Signals'!G11 -> 0.38498155 | D40: ='Valuation Signals'!G9 -> 2.933072 | E40: ='Valuation Signals'!G5 -> 5.6950538
A42: Read across each row. USD100m ARR is not a single economic outcome — Cartrack and Microlise sit at comparable ARR with opposite margins and a ~14x gap in enterprise value per dollar of sales. Quartix is profitable at half the size. Specify the 2030 goal as ARR AND margin.
A44: Subscribers required for USD100m ARR, by monthly ARPU
A45: ARPU (USD per month) | B45: Implied annual ARPU (USD) | C45: Subscribers required | D45: Multiple of Cartrack's FY2019 base | E45: Comment
A46: 5 | B46: =A46*12 -> 60 | C46: =IFERROR($B$7*1000000/B46,"") -> 1666666.7 | D46: =IFERROR(C46/'Karooooo Path'!C19,"") -> 1.7346692 | E46: Low-end Indonesian SME price point.
A47: 8 | B47: =A47*12 -> 96 | C47: =IFERROR($B$7*1000000/B47,"") -> 1041666.7 | D47: =IFERROR(C47/'Karooooo Path'!C19,"") -> 1.0841682 | E47: Typical Indonesian mid-market FMS subscription.
A48: 9.63 | B48: =A48*12 -> 115.56 | C48: =IFERROR($B$7*1000000/B48,"") -> 865351.33 | D48: =IFERROR(C48/'Karooooo Path'!C19,"") -> 0.90065897 | E48: Cartrack's actual FY2019 ARPU — the benchmark row above.
A49: 12 | B49: =A49*12 -> 144 | C49: =IFERROR($B$7*1000000/B49,"") -> 694444.44 | D49: =IFERROR(C49/'Karooooo Path'!C19,"") -> 0.72277882 | E49: Requires clear value-add well beyond basic tracking.
A50: 15 | B50: =A50*12 -> 180 | C50: =IFERROR($B$7*1000000/B50,"") -> 555555.56 | D50: =IFERROR(C50/'Karooooo Path'!C19,"") -> 0.57822306 | E50: Multi-product: telematics + video + fuel + driver app.
A51: 20 | B51: =A51*12 -> 240 | C51: =IFERROR($B$7*1000000/B51,"") -> 416666.67 | D51: =IFERROR(C51/'Karooooo Path'!C19,"") -> 0.43366729 | E51: Enterprise-only mix; a much smaller addressable base.
A53: Headcount implied by peer revenue-per-employee
A54: Benchmark | B54: Revenue per employee (USD k) | C54: Headcount implied at USD100m ARR | D54: Comment
A55: Karooooo today (FY2026) | B55: ='Current Position'!K5 -> 68.831658 | C55: =IFERROR($B$7*1000/B55,"") -> 1452.8199 | D55: Emerging-market cost base with in-house installation crews. The most relevant analogue.
A56: Motive (LTM Sep-25) | B56: ='Current Position'!K8 -> 95.164153 | C56: =IFERROR($B$7*1000/B56,"") -> 1050.8159 | D56: 78% of Motive's staff are offshore, which is why this looks efficient despite the losses.
A57: Gurtam (CY2025) | B57: ='Current Position'!K11 -> 110.0295 | C57: =IFERROR($B$7*1000/B57,"") -> 908.84718 | D57: Pure software / channel model — no installation labour at all. The upper bound.
A59: Notes & definitions
A60: This sheet is a benchmarking tool, not a financial model. It answers "what would McEasy have to look like", not "how does McEasy get there". Building the second thing is the next piece of work.
A61: The ARPU table is the crux. At USD8 per subscriber per month McEasy needs a little over one million subscribers to reach USD100m ARR — more than Cartrack had in its entire global base in FY2019, in a single country. Either the ARPU assumption rises materially, or the subscriber target becomes the binding constraint on the 2030 goal.

Sheet Assumptions
A1: Assumptions & FX
A2: Blue = hardcoded input you can change. Every FX-converted figure elsewhere in this workbook points back to these cells.
A4: Assumption | B4: Value | C4: Unit | D4: Basis / source
A5: USD/ZAR — average, Cartrack FY2018 (Mar-17 to Feb-18) | B5: 12.9 | C5: ZAR per USD | D5: Period average. Subscription revenue ZAR1,165.5m / 12.90 = USD90m — the year before Cartrack crossed USD100m subscription ARR.
A6: USD/ZAR — average, Cartrack FY2019 (Mar-18 to Feb-19) | B6: 13.7 | C6: ZAR per USD | D6: Period average. Cross-check: FY2019 subscription revenue ZAR1,520.5m / 13.70 = USD111m, consistent with Cartrack crossing ~USD100m subscription ARR during FY2019.
A7: USD/ZAR — average, FY2020 (Mar-19 to Feb-20) | B7: 14.6 | C7: ZAR per USD | D7: Period average.
A8: USD/ZAR — average, FY2022 (Mar-21 to Feb-22) | B8: 14.9 | C8: ZAR per USD | D8: Period average.
A9: USD/ZAR — average, FY2023 (Mar-22 to Feb-23) | B9: 17.4 | C9: ZAR per USD | D9: Period average.
A10: USD/ZAR — average, FY2024 (Mar-23 to Feb-24) | B10: 18.7 | C10: ZAR per USD | D10: Period average.
A11: USD/ZAR — average, FY2025 (Mar-24 to Feb-25) | B11: 18.63 | C11: ZAR per USD | D11: Implied by Karooooo's own disclosure: FY2025 EPS ZAR29.81 = USD1.60.
A12: USD/ZAR — average, FY2026 (Mar-25 to Feb-26) | B12: 15.92 | C12: ZAR per USD | D12: Implied by Karooooo's own disclosure: FY2026 EPS ZAR32.17 = USD2.02. Cross-check: ARR ZAR5,179m = USD325m implies 15.94.
A13: GBP/USD — average, calendar 2025 | B13: 1.319 | C13: USD per GBP | D13: 2025 full-year average, 1.3190. Applied to Microlise and Quartix. Note this rate MULTIPLIES GBP to reach USD, whereas the ZAR and CNY rates DIVIDE.
A14: USD/CNY — average, calendar 2025 | B14: 7.1873 | C14: CNY per USD | D14: 2025 full-year average, 7.1873. Applied to Queclink and Streamax.
A15: McEasy target ARR | B15: 100 | C15: USD m | D15: User-stated 2030 goal.
A16: McEasy target year | B16: 2030 | C16: calendar year | D16: User-stated.
A18: Data-confidence legend
A19: H — High | D19: Taken directly from an audited filing, SEC submission, or company press release.
A20: M — Medium | D20: Derived by arithmetic from disclosed figures (FX conversion, margin calculation, growth-rate roll-forward). Stated method, no judgement calls.
A21: L — Low | D21: Third-party estimate (Revelio, Growjo, Latka, PitchBook) or a private company that does not publish financials. Directional only — do not put these in a board pack without a second source.
A22: n/d | D22: Not disclosed and not reliably estimable. Left blank on purpose.

Sheet Sources
A1: Sources
A2: Every figure in this workbook traces to one of these. Retrieved 10-Aug-2026.
A4: Company | B4: What it supports | C4: Document | D4: URL
A5: Karooooo | B5: FY2026 revenue, subscription revenue, ARR, subscribers, segment split, margins, cash flow, FY2027 guidance | C5: Form 6-K, Q4 & FY2026 results release (13-May-2026) | D5: https://www.sec.gov/Archives/edgar/data/1828102/000121390026055767/ea029054101ex99-1.htm
A6: Karooooo | B6: Same, mirrored with full segment and geographic tables | C6: StockTitan filing summary of the FY2026 6-K | D6: https://www.stocktitan.net/sec-filings/KARO/6-k-karooooo-ltd-current-report-foreign-issuer-cc4ab432d528.html
A7: Karooooo | B7: FY2026 press release, dividend, adjusted FCF, regional commentary | C7: Karooooo, "Delivers Accelerating Subscription Revenue Growth and Strong Cash Flow in FY 2026" | D7: https://www.businesswire.com/news/home/20260513986164/en/
A8: Karooooo | B8: FY2022-FY2026 revenue, gross profit, operating income, net income, FCF history | C8: StockAnalysis.com financial statements, KARO | D8: https://stockanalysis.com/stocks/karo/financials/
A9: Karooooo | B9: FY2025 revenue by geography (South Africa, APAC/ME/USA, Europe, Africa-other) | C9: TradingKey revenue breakdown, NASDAQ: KARO | D9: https://www.tradingkey.com/markets/stocks/nasdaq-karo/revenue
A10: Karooooo | B10: FY2026 20-F (filed Jun-2026) — referenced for headcount and geography | C10: Form 20-F, FY2026 | D10: https://www.sec.gov/Archives/edgar/data/0001828102/000121390026066795/ea0293645-20f_karooooo.htm
A11: Cartrack | B11: FY2019 full income statement, cash flow, subscribers and the complete geographic segment table — the USD100m-ARR vintage | C11: JSE SENS: Summarised Preliminary Consolidated Audited Results, year ended 28-Feb-2019 | D11: https://www.sharenet.co.za/v3/sens_display.php?tdate=20190528070700&seq=3
A12: Cartrack | B12: FY2020 subscription revenue ZAR1,888m (97% of total) and 1,126,515 subscribers | C12: Cartrack 2020 Integrated Annual Report | D12: https://www.sharedata.co.za/data/015736/pdfs/CARTRACK_ar_feb20.pdf
A13: Karooooo | B13: Headcount indication (>5,000 group staff) | C13: Q4 & FY2025 earnings call transcript | D13: https://karooooo.com/wp-content/uploads/2025/05/Transcript-Q4-and-FY-2025.pdf
A14: Karooooo | B14: Third-party headcount estimate, 4,550 as at Mar-2026 | C14: Revelio Labs company profile, Cartrack | D14: https://www.reveliolabs.com/companies/cartrack/employees
A15: Ituran | B15: FY2025 revenue USD359.0m, net income USD58.0m, EBITDA USD96.2m, operating cash flow USD88.6m, 2.63m subscribers, 74/26 services-products split, Q4 geography 55/23/22 | C15: Q4 & FY2025 results press release (05-Mar-2026) | D15: https://www.prnewswire.com/news-releases/ituran-presents-fourth-quarter--full-year-2025-results-302705204.html
... A50: McEasy | B50: 2030 volume assumption: ~900k-1m vehicles at USD8-9 per vehicle per month, Southeast-Asia-weighted. NOT PRESENT IN THE MODEL — supplied by Grady Kusmulyadi in conversation on 11-Aug-2026. Every per-vehicle figure in this workbook depends on it. | C50: Verbal, unmodelled. Flagged yellow throughout. | D50: internal
A52: Notes & definitions
A53: Third-party estimates (Tracxn, Growjo, Latka, Revelio) are flagged L on every sheet. They are the only public data for Geotab, Lytx and Gurtam. Do not present them to a board without a second independent source.
A54: SEC EDGAR pages may need a browser user-agent header; every SEC figure above was also cross-checked against a press-release mirror.
